Workbook

Sheet Сводка
A1: Финмодель
A2: Кейс: до 10 млрд ₽ за 3 года, окупаемость до 3 лет. Период: Q1 2027 – Q4 2029. Деньги — млн ₽.
A3: Синий — ввод; чёрный — формула; зелёный — ссылка на лист; жёлтый — ключевое допущение.
A4: Допущения менять только на листе «Допущения».
A6: 1. Ключевые результаты | B6: Пессимист | C6: База | D6: Оптимист
A7: Окупаемость, квартал проекта (накопленный поток ≥ 0) | B7: =Модель_Пессимист!C117 -> не окупается | C7: =Модель_База!C117 -> не окупается | D7: =Модель_Оптимист!C117 -> 7
A8: Дисконтированная окупаемость, квартал проекта (ставка 15%) | B8: =Модель_Пессимист!C118 -> не окупается | C8: =Модель_База!C118 -> не окупается | D8: =Модель_Оптимист!C118 -> 7
A9: Окупаемость, месяцев | B9: =Модель_Пессимист!C119 -> н/д | C9: =Модель_База!C119 -> н/д | D9: =Модель_Оптимист!C119 -> 21
A10: Пиковая потребность в финансировании, млн ₽ | B10: =Модель_Пессимист!C120 -> 478.11005 | C10: =Модель_База!C120 -> 170.25678 | D10: =Модель_Оптимист!C120 -> 146.93276
A11: Доля от лимита 10 млрд ₽ | B11: =Модель_Пессимист!C121 -> 0.047811005 | C11: =Модель_База!C121 -> 0.017025678 | D11: =Модель_Оптимист!C121 -> 0.014693276
A12: Дополнительная выручка за 3 года, млн ₽ | B12: =Модель_Пессимист!C122 -> 58.03787 | C12: =Модель_База!C122 -> 630.44877 | D12: =Модель_Оптимист!C122 -> 2301.8644
A13: Затраты за 3 года, млн ₽ | B13: =Модель_Пессимист!C123 -> 527.44224 | C13: =Модель_База!C123 -> 642.26951 | D13: =Модель_Оптимист!C123 -> 927.36706
A14: Накопленный чистый поток за 3 года, млн ₽ | B14: =Модель_Пессимист!C124 -> -478.11005 | C14: =Модель_База!C124 -> -106.38806 | D14: =Модель_Оптимист!C124 -> 1029.2177
A15: NPV за 3 года, млн ₽ | B15: =Модель_Пессимист!C125 -> -381.43983 | C15: =Модель_База!C125 -> -106.50067 | D15: =Модель_Оптимист!C125 -> 714.17775
A16: ROI за 3 года | B16: =Модель_Пессимист!C126 -> -0.90646902 | C16: =Модель_База!C126 -> -0.16564395 | D16: =Модель_Оптимист!C126 -> 1.1098277
A17: Run-rate чистого потока на Q12, млн ₽/год | B17: =Модель_Пессимист!C127 -> -164.1546 | C17: =Модель_База!C127 -> 66.667072 | D17: =Модель_Оптимист!C127 -> 844.39361
A18: Отзывов за 3 года, тыс. шт. | B18: =Модель_Пессимист!C128 -> 1476.0051 | C18: =Модель_База!C128 -> 10264.777 | D18: =Модель_Оптимист!C128 -> 18045.687
A19: Чистый прирост сделок за 3 года, тыс. шт. | B19: =Модель_Пессимист!C129 -> 216.97274 | C19: =Модель_База!C129 -> 1992.0082 | D19: =Модель_Оптимист!C129 -> 6600.21
A20: Мин. прирост конверсии: простая окупаемость за 12 кв. | B20: =Модель_Пессимист!C135 -> 0.3881844 | C20: =Модель_База!C135 -> 0.060507692 | D20: =Модель_Оптимист!C135 -> 0.028531037
A21: Мин. прирост конверсии: дисконтированная окупаемость за 12 кв. | B21: =Модель_Пессимист!C134 -> 0.42694901 | C21: =Модель_База!C134 -> 0.064461692 | D21: =Модель_Оптимист!C134 -> 0.031061689
A22: Заложенный прирост конверсии | B22: =Модель_Пессимист!C132 -> 0.04 | C22: =Модель_База!C132 -> 0.05 | D22: =Модель_Оптимист!C132 -> 0.08
A24: Проверки по условиям кейса
A25: Бюджет: пиковая потребность ≤ лимита (10 млрд ₽) | B25: =IF(B10<=Допущения!$C$6,"ОК","Превышен лимит") -> ОК | C25: =IF(C10<=Допущения!$C$6,"ОК","Превышен лимит") -> ОК | D25: =IF(D10<=Допущения!$C$6,"ОК","Превышен лимит") -> ОК
A26: Срок: окупаемость ≤ 12 кварталов | B26: =IF(ISNUMBER(B7),IF(B7<=Допущения!$C$7,"ОК","Дольше 3 лет"),"Не окупается за 3 года") -> Не окупается за 3 года | C26: =IF(ISNUMBER(C7),IF(C7<=Допущения!$C$7,"ОК","Дольше 3 лет"),"Не окупается за 3 года") -> Не окупается за 3 года | D26: =IF(ISNUMBER(D7),IF(D7<=Допущения!$C$7,"ОК","Дольше 3 лет"),"Не окупается за 3 года") -> ОК
A27: Срок: дисконтированная окупаемость ≤ 12 кварталов | B27: =IF(ISNUMBER(B8),IF(B8<=Допущения!$C$7,"ОК","Дольше 3 лет"),"Не окупается за 3 года") -> Не окупается за 3 года | C27: =IF(ISNUMBER(C8),IF(C8<=Допущения!$C$7,"ОК","Дольше 3 лет"),"Не окупается за 3 года") -> Не окупается за 3 года | D27: =IF(ISNUMBER(D8),IF(D8<=Допущения!$C$7,"ОК","Дольше 3 лет"),"Не окупается за 3 года") -> ОК
A28: Контрольное условие: чистый эффект на сделки ≥ 0 (контакты не падают) | B28: =IF(B19>=0,"ОК","Сделки падают") -> ОК | C28: =IF(C19>=0,"ОК","Сделки падают") -> ОК | D28: =IF(D19>=0,"ОК","Сделки падают") -> ОК
A30: 2. По годам — Пессимист, млн ₽ | B30: 2027 | C30: 2028 | D30: 2029 | E30: Итого
A31: Эффект 1: конверсия в сделку | B31: =Модель_Пессимист!Q84 -> 0.9926345 | C31: =Модель_Пессимист!R84 -> 13.232303 | D31: =Модель_Пессимист!S84 -> 37.967258 | E31: =Модель_Пессимист!T84 -> 52.192196
A32: Эффект 2: продвижение новых объявлений | B32: =Модель_Пессимист!Q85 -> 0 | C32: =Модель_Пессимист!R85 -> 0.022598754 | D32: =Модель_Пессимист!S85 -> 0.095471631 | E32: =Модель_Пессимист!T85 -> 0.11807038
A33: Эффект 2: сделки по новым объявлениям | B33: =Модель_Пессимист!Q86 -> 0 | C33: =Модель_Пессимист!R86 -> 0.058756759 | D33: =Модель_Пессимист!S86 -> 0.25815529 | E33: =Модель_Пессимист!T86 -> 0.31691205
A34: Эффект 3: визиты (реклама, рекомендации) | B34: =Модель_Пессимист!Q89 -> 0.115668 | C34: =Модель_Пессимист!R89 -> 1.439424 | D34: =Модель_Пессимист!S89 -> 3.8556 | E34: =Модель_Пессимист!T89 -> 5.410692
A35: Эффект 4: удержание | B35: =Модель_Пессимист!Q90 -> 0 | C35: =Модель_Пессимист!R90 -> 0 | D35: =Модель_Пессимист!S90 -> 0 | E35: =Модель_Пессимист!T90 -> 0
A36: Дополнительная выручка всего | B36: =Модель_Пессимист!Q91 -> 1.1083025 | C36: =Модель_Пессимист!R91 -> 14.753083 | D36: =Модель_Пессимист!S91 -> 42.176485 | E36: =Модель_Пессимист!T91 -> 58.03787
A37: Маржинальный доход | B37: =Модель_Пессимист!Q92 -> 0.94205712 | C37: =Модель_Пессимист!R92 -> 12.54012 | D37: =Модель_Пессимист!S92 -> 35.850012 | E37: =Модель_Пессимист!T92 -> 49.33219
A38: Затраты: команда разработки | B38: =Модель_Пессимист!Q96 -> 81 | C38: =Модель_Пессимист!R96 -> 110.808 | D38: =Модель_Пессимист!S96 -> 125.9712 | E38: =Модель_Пессимист!T96 -> 317.7792
A39: Затраты: модерация (ИИ + ручная) | B39: =Модель_Пессимист!Q98+Модель_Пессимист!Q99 -> 0.19807673 | C39: =Модель_Пессимист!R98+Модель_Пессимист!R99 -> 2.5389034 | D39: =Модель_Пессимист!S98+Модель_Пессимист!S99 -> 7.0046533 | E39: =Модель_Пессимист!T98+Модель_Пессимист!T99 -> 9.7416334
A40: Затраты: ИИ и инфраструктура | B40: =Модель_Пессимист!Q100 -> 7.5600233 | C40: =Модель_Пессимист!R100 -> 10.769365 | D40: =Модель_Пессимист!S100 -> 12.122622 | E40: =Модель_Пессимист!T100 -> 30.45201
A41: Затраты: мотивация авторов | B41: =Модель_Пессимист!Q101 -> 0.6002325 | C41: =Модель_Пессимист!R101 -> 7.6936468 | D41: =Модель_Пессимист!S101 -> 21.226222 | E41: =Модель_Пессимист!T101 -> 29.520101
A42: Затраты: маркетинг | B42: =Модель_Пессимист!Q102 -> 60 | C42: =Модель_Пессимист!R102 -> 16 | D42: =Модель_Пессимист!S102 -> 16 | E42: =Модель_Пессимист!T102 -> 92
A43: Затраты: резерв | B43: =Модель_Пессимист!Q104 -> 14.935833 | C43: =Модель_Пессимист!R104 -> 14.780991 | D43: =Модель_Пессимист!S104 -> 18.23247 | E43: =Модель_Пессимист!T104 -> 47.949294
A44: Затраты всего | B44: =Модель_Пессимист!Q105 -> 164.29417 | C44: =Модель_Пессимист!R105 -> 162.59091 | D44: =Модель_Пессимист!S105 -> 200.55717 | E44: =Модель_Пессимист!T105 -> 527.44224
A45: Чистый денежный поток | B45: =Модель_Пессимист!Q108 -> -163.35211 | C45: =Модель_Пессимист!R108 -> -150.05079 | D45: =Модель_Пессимист!S108 -> -164.70715 | E45: =Модель_Пессимист!T108 -> -478.11005
A47: 2. По годам — База, млн ₽ | B47: 2027 | C47: 2028 | D47: 2029 | E47: Итого
A48: Эффект 1: конверсия в сделку | B48: =Модель_База!Q84 -> 11.625318 | C48: =Модель_База!R84 -> 169.81671 | D48: =Модель_База!S84 -> 366.48719 | E48: =Модель_База!T84 -> 547.92922
A49: Эффект 2: продвижение новых объявлений | B49: =Модель_База!Q85 -> 0 | C49: =Модель_База!R85 -> 1.115195 | D49: =Модель_База!S85 -> 3.8551512 | E49: =Модель_База!T85 -> 4.9703462
A50: Эффект 2: сделки по новым объявлениям | B50: =Модель_База!Q86 -> 0 | C50: =Модель_База!R86 -> 2.4627223 | D50: =Модель_База!S86 -> 9.0242665 | E50: =Модель_База!T86 -> 11.486989
A51: Эффект 3: визиты (реклама, рекомендации) | B51: =Модель_База!Q89 -> 1.9123776 | C51: =Модель_База!R89 -> 23.02344 | D51: =Модель_База!S89 -> 41.1264 | E51: =Модель_База!T89 -> 66.062218
A52: Эффект 4: удержание | B52: =Модель_База!Q90 -> 0 | C52: =Модель_База!R90 -> 0 | D52: =Модель_База!S90 -> 0 | E52: =Модель_База!T90 -> 0
A53: Дополнительная выручка всего | B53: =Модель_База!Q91 -> 13.537696 | C53: =Модель_База!R91 -> 196.41807 | D53: =Модель_База!S91 -> 420.49301 | E53: =Модель_База!T91 -> 630.44877
A54: Маржинальный доход | B54: =Модель_База!Q92 -> 11.507041 | C54: =Модель_База!R92 -> 166.95536 | D54: =Модель_База!S92 -> 357.41905 | E54: =Модель_База!T92 -> 535.88145
A55: Затраты: команда разработки | B55: =Модель_База!Q96 -> 68.85 | C55: =Модель_База!R96 -> 94.1868 | D55: =Модель_База!S96 -> 107.07552 | E55: =Модель_База!T96 -> 270.11232
A56: Затраты: модерация (ИИ + ручная) | B56: =Модель_База!Q98+Модель_База!Q99 -> 1.2939484 | C56: =Модель_База!R98+Модель_База!R99 -> 17.831451 | D56: =Модель_База!S98+Модель_База!S99 -> 36.304394 | E56: =Модель_База!T98+Модель_База!T99 -> 55.429794
A57: Затраты: ИИ и инфраструктура | B57: =Модель_База!Q100 -> 7.9792402 | C57: =Модель_База!R100 -> 16.604241 | D57: =Модель_База!S100 -> 23.446072 | E57: =Модель_База!T100 -> 48.029553
A58: Затраты: мотивация авторов | B58: =Модель_База!Q101 -> 2.995251 | C58: =Модель_База!R101 -> 41.276507 | D58: =Модель_База!S101 -> 84.03795 | E58: =Модель_База!T101 -> 128.30971
A59: Затраты: маркетинг | B59: =Модель_База!Q102 -> 50 | C59: =Модель_База!R102 -> 16 | D59: =Модель_База!S102 -> 16 | E59: =Модель_База!T102 -> 82
A60: Затраты: резерв | B60: =Модель_База!Q104 -> 13.111844 | C60: =Модель_База!R104 -> 18.5899 | D60: =Модель_База!S104 -> 26.686394 | E60: =Модель_База!T104 -> 58.388138
A61: Затраты всего | B61: =Модель_База!Q105 -> 144.23028 | C61: =Модель_База!R105 -> 204.4889 | D61: =Модель_База!S105 -> 293.55033 | E61: =Модель_База!T105 -> 642.26951
A62: Чистый денежный поток | B62: =Модель_База!Q108 -> -132.72324 | C62: =Модель_База!R108 -> -37.533542 | D62: =Модель_База!S108 -> 63.868725 | E62: =Модель_База!T108 -> -106.38806
A64: 2. По годам — Оптимист, млн ₽ | B64: 2027 | C64: 2028 | D64: 2029 | E64: Итого
A65: Эффект 1: конверсия в сделку | B65: =Модель_Оптимист!Q84 -> 46.091358 | C65: =Модель_Оптимист!R84 -> 598.929 | D65: =Модель_Оптимист!S84 -> 1195.5211 | E65: =Модель_Оптимист!T84 -> 1840.5414
A66: Эффект 2: продвижение новых объявлений | B66: =Модель_Оптимист!Q85 -> 0 | C66: =Модель_Оптимист!R85 -> 7.8513435 | D66: =Модель_Оптимист!S85 -> 24.529861 | E66: =Модель_Оптимист!T85 -> 32.381205
A67: Эффект 2: сделки по новым объявлениям | B67: =Модель_Оптимист!Q86 -> 0 | C67: =Модель_Оптимист!R86 -> 13.4415 | D67: =Модель_Оптимист!S86 -> 44.934781 | E67: =Модель_Оптимист!T86 -> 58.376281
A68: Эффект 3: визиты (реклама, рекомендации) | B68: =Модель_Оптимист!Q89 -> 8.664084 | C68: =Модель_Оптимист!R89 -> 88.151501 | D68: =Модель_Оптимист!S89 -> 138.62534 | E68: =Модель_Оптимист!T89 -> 235.44093
A69: Эффект 4: удержание | B69: =Модель_Оптимист!Q90 -> 4.9725 | C69: =Модель_Оптимист!R90 -> 50.592 | D69: =Модель_Оптимист!S90 -> 79.56 | E69: =Модель_Оптимист!T90 -> 135.1245
A70: Дополнительная выручка всего | B70: =Модель_Оптимист!Q91 -> 59.727942 | C70: =Модель_Оптимист!R91 -> 758.96534 | D70: =Модель_Оптимист!S91 -> 1483.1711 | E70: =Модель_Оптимист!T91 -> 2301.8644
A71: Маржинальный доход | B71: =Модель_Оптимист!Q92 -> 50.768751 | C71: =Модель_Оптимист!R92 -> 645.12054 | D71: =Модель_Оптимист!S92 -> 1260.6954 | E71: =Модель_Оптимист!T92 -> 1956.5847
A72: Затраты: команда разработки | B72: =Модель_Оптимист!Q96 -> 81 | C72: =Модель_Оптимист!R96 -> 110.808 | D72: =Модель_Оптимист!S96 -> 125.9712 | E72: =Модель_Оптимист!T96 -> 317.7792
A73: Затраты: модерация (ИИ + ручная) | B73: =Модель_Оптимист!Q98+Модель_Оптимист!Q99 -> 2.41956 | C73: =Модель_Оптимист!R98+Модель_Оптимист!R99 -> 29.383834 | D73: =Модель_Оптимист!S98+Модель_Оптимист!S99 -> 54.815904 | E73: =Модель_Оптимист!T98+Модель_Оптимист!T99 -> 86.619298
A74: Затраты: ИИ и инфраструктура | B74: =Модель_Оптимист!Q100 -> 10.00815 | C74: =Модель_Оптимист!R100 -> 24.243264 | D74: =Модель_Оптимист!S100 -> 34.83996 | E74: =Модель_Оптимист!T100 -> 69.091374
A75: Затраты: мотивация авторов | B75: =Модель_Оптимист!Q101 -> 6.3009375 | C75: =Модель_Оптимист!R101 -> 76.5204 | D75: =Модель_Оптимист!S101 -> 142.74975 | E75: =Модель_Оптимист!T101 -> 225.57109
A76: Затраты: маркетинг | B76: =Модель_Оптимист!Q102 -> 80 | C76: =Модель_Оптимист!R102 -> 32 | D76: =Модель_Оптимист!S102 -> 32 | E76: =Модель_Оптимист!T102 -> 144
A77: Затраты: резерв | B77: =Модель_Оптимист!Q104 -> 17.972865 | C77: =Модель_Оптимист!R104 -> 27.29555 | D77: =Модель_Оптимист!S104 -> 39.037681 | E77: =Модель_Оптимист!T104 -> 84.306096
A78: Затраты всего | B78: =Модель_Оптимист!Q105 -> 197.70151 | C78: =Модель_Оптимист!R105 -> 300.25105 | D78: =Модель_Оптимист!S105 -> 429.4145 | E78: =Модель_Оптимист!T105 -> 927.36706
A79: Чистый денежный поток | B79: =Модель_Оптимист!Q108 -> -146.93276 | C79: =Модель_Оптимист!R108 -> 344.86949 | D79: =Модель_Оптимист!S108 -> 831.28092 | E79: =Модель_Оптимист!T108 -> 1029.2177
A81: 3. Чувствительность: накопленный поток за 3 года, млн ₽, к приросту конверсии
A82: Прирост конверсии (остальное — как в сценарии) | B82: Пессимист | C82: База | D82: Оптимист
A83: 0.01 | B83: =IF(Модель_Пессимист!$C$130>0,Модель_Пессимист!$O$109+Модель_Пессимист!$C$131*(($A83*Модель_Пессимист!$C$32-Модель_Пессимист!$C$31)/Модель_Пессимист!$C$130-1),"н/д") -> -519.3046 | C83: =IF(Модель_База!$C$130>0,Модель_База!$O$109+Модель_База!$C$131*(($A83*Модель_База!$C$32-Модель_База!$C$31)/Модель_База!$C$130-1),"н/д") -> -511.37922 | D83: =IF(Модель_Оптимист!$C$130>0,Модель_Оптимист!$O$109+Модель_Оптимист!$C$131*(($A83*Модель_Оптимист!$C$32-Модель_Оптимист!$C$31)/Модель_Оптимист!$C$130-1),"н/д") -> -370.56255
A84: 0.02 | B84: =IF(Модель_Пессимист!$C$130>0,Модель_Пессимист!$O$109+Модель_Пессимист!$C$131*(($A84*Модель_Пессимист!$C$32-Модель_Пессимист!$C$31)/Модель_Пессимист!$C$130-1),"н/д") -> -505.57309 | C84: =IF(Модель_База!$C$130>0,Модель_База!$O$109+Модель_База!$C$131*(($A84*Модель_База!$C$32-Модель_База!$C$31)/Модель_База!$C$130-1),"н/д") -> -410.13143 | D84: =IF(Модель_Оптимист!$C$130>0,Модель_Оптимист!$O$109+Модель_Оптимист!$C$131*(($A84*Модель_Оптимист!$C$32-Модель_Оптимист!$C$31)/Модель_Оптимист!$C$130-1),"н/д") -> -170.59395
A85: 0.03 | B85: =IF(Модель_Пессимист!$C$130>0,Модель_Пессимист!$O$109+Модель_Пессимист!$C$131*(($A85*Модель_Пессимист!$C$32-Модель_Пессимист!$C$31)/Модель_Пессимист!$C$130-1),"н/д") -> -491.84157 | C85: =IF(Модель_База!$C$130>0,Модель_База!$O$109+Модель_База!$C$131*(($A85*Модель_База!$C$32-Модель_База!$C$31)/Модель_База!$C$130-1),"н/д") -> -308.88364 | D85: =IF(Модель_Оптимист!$C$130>0,Модель_Оптимист!$O$109+Модель_Оптимист!$C$131*(($A85*Модель_Оптимист!$C$32-Модель_Оптимист!$C$31)/Модель_Оптимист!$C$130-1),"н/д") -> 29.374648
A86: 0.04 | B86: =IF(Модель_Пессимист!$C$130>0,Модель_Пессимист!$O$109+Модель_Пессимист!$C$131*(($A86*Модель_Пессимист!$C$32-Модель_Пессимист!$C$31)/Модель_Пессимист!$C$130-1),"н/д") -> -478.11005 | C86: =IF(Модель_База!$C$130>0,Модель_База!$O$109+Модель_База!$C$131*(($A86*Модель_База!$C$32-Модель_База!$C$31)/Модель_База!$C$130-1),"н/д") -> -207.63585 | D86: =IF(Модель_Оптимист!$C$130>0,Модель_Оптимист!$O$109+Модель_Оптимист!$C$131*(($A86*Модель_Оптимист!$C$32-Модель_Оптимист!$C$31)/Модель_Оптимист!$C$130-1),"н/д") -> 229.34325
A87: 0.05 | B87: =IF(Модель_Пессимист!$C$130>0,Модель_Пессимист!$O$109+Модель_Пессимист!$C$131*(($A87*Модель_Пессимист!$C$32-Модель_Пессимист!$C$31)/Модель_Пессимист!$C$130-1),"н/д") -> -464.37853 | C87: =IF(Модель_База!$C$130>0,Модель_База!$O$109+Модель_База!$C$131*(($A87*Модель_База!$C$32-Модель_База!$C$31)/Модель_База!$C$130-1),"н/д") -> -106.38806 | D87: =IF(Модель_Оптимист!$C$130>0,Модель_Оптимист!$O$109+Модель_Оптимист!$C$131*(($A87*Модель_Оптимист!$C$32-Модель_Оптимист!$C$31)/Модель_Оптимист!$C$130-1),"н/д") -> 429.31185
A88: 0.06 | B88: =IF(Модель_Пессимист!$C$130>0,Модель_Пессимист!$O$109+Модель_Пессимист!$C$131*(($A88*Модель_Пессимист!$C$32-Модель_Пессимист!$C$31)/Модель_Пессимист!$C$130-1),"н/д") -> -450.64701 | C88: =IF(Модель_База!$C$130>0,Модель_База!$O$109+Модель_База!$C$131*(($A88*Модель_База!$C$32-Модель_База!$C$31)/Модель_База!$C$130-1),"н/д") -> -5.1402691 | D88: =IF(Модель_Оптимист!$C$130>0,Модель_Оптимист!$O$109+Модель_Оптимист!$C$131*(($A88*Модель_Оптимист!$C$32-Модель_Оптимист!$C$31)/Модель_Оптимист!$C$130-1),"н/д") -> 629.28045
A89: 0.08 | B89: =IF(Модель_Пессимист!$C$130>0,Модель_Пессимист!$O$109+Модель_Пессимист!$C$131*(($A89*Модель_Пессимист!$C$32-Модель_Пессимист!$C$31)/Модель_Пессимист!$C$130-1),"н/д") -> -423.18398 | C89: =IF(Модель_База!$C$130>0,Модель_База!$O$109+Модель_База!$C$131*(($A89*Модель_База!$C$32-Модель_База!$C$31)/Модель_База!$C$130-1),"н/д") -> 197.35531 | D89: =IF(Модель_Оптимист!$C$130>0,Модель_Оптимист!$O$109+Модель_Оптимист!$C$131*(($A89*Модель_Оптимист!$C$32-Модель_Оптимист!$C$31)/Модель_Оптимист!$C$130-1),"н/д") -> 1029.2177
A90: 0.1 | B90: =IF(Модель_Пессимист!$C$130>0,Модель_Пессимист!$O$109+Модель_Пессимист!$C$131*(($A90*Модель_Пессимист!$C$32-Модель_Пессимист!$C$31)/Модель_Пессимист!$C$130-1),"н/д") -> -395.72094 | C90: =IF(Модель_База!$C$130>0,Модель_База!$O$109+Модель_База!$C$131*(($A90*Модель_База!$C$32-Модель_База!$C$31)/Модель_База!$C$130-1),"н/д") -> 399.85089 | D90: =IF(Модель_Оптимист!$C$130>0,Модель_Оптимист!$O$109+Модель_Оптимист!$C$131*(($A90*Модель_Оптимист!$C$32-Модель_Оптимист!$C$31)/Модель_Оптимист!$C$130-1),"н/д") -> 1429.1549
A91: Линейно по uplift; «н/д» — если чистый эффект на конверсию ≤ 0.
A93: 4. Накопленный чистый денежный поток по кварталам, млн ₽
A94: Квартал | B94: =Модель_Пессимист!D7 -> Q1 2027 | C94: =Модель_Пессимист!E7 -> Q2 2027 | D94: =Модель_Пессимист!F7 -> Q3 2027 | E94: =Модель_Пессимист!G7 -> Q4 2027 | F94: =Модель_Пессимист!H7 -> Q1 2028 | G94: =Модель_Пессимист!I7 -> Q2 2028 | H94: =Модель_Пессимист!J7 -> Q3 2028 | I94: =Модель_Пессимист!K7 -> Q4 2028 | ... M94: =Модель_Пессимист!O7 -> Q4 2029
A95: Пессимист | B95: =Модель_Пессимист!D109 -> -22.275 | C95: =Модель_Пессимист!E109 -> -47.3 | D95: =Модель_Пессимист!F109 -> -105.3257 | E95: =Модель_Пессимист!G109 -> -163.35211 | F95: =Модель_Пессимист!H109 -> -200.91748 | G95: =Модель_Пессимист!I109 -> -238.45237 | H95: =Модель_Пессимист!J109 -> -275.94648 | I95: =Модель_Пессимист!K109 -> -313.40289 | ... M95: =Модель_Пессимист!O109 -> -478.11005
A96: База | B96: =Модель_База!D109 -> -18.93375 | C96: =Модель_База!E109 -> -40.6175 | D96: =Модель_База!F109 -> -88.012176 | E96: =Модель_База!G109 -> -132.72324 | F96: =Модель_База!H109 -> -150.20765 | G96: =Модель_База!I109 -> -162.02472 | H96: =Модель_База!J109 -> -168.26319 | I96: =Модель_База!K109 -> -170.25678 | ... M96: =Модель_База!O109 -> -106.38806
A97: Оптимист | B97: =Модель_Оптимист!D109 -> -22.275 | C97: =Модель_Оптимист!E109 -> -47.85 | D97: =Модель_Оптимист!F109 -> -105.40483 | E97: =Модель_Оптимист!G109 -> -146.93276 | F97: =Модель_Оптимист!H109 -> -103.15781 | G97: =Модель_Оптимист!I109 -> -27.096557 | H97: =Модель_Оптимист!J109 -> 76.495943 | I97: =Модель_Оптимист!K109 -> 197.93673 | ... M97: =Модель_Оптимист!O109 -> 1029.2177
A98: Лимит инвестиций (отрицательная граница) | B98: =-Допущения!$C$6 -> -10000 | C98: =-Допущения!$C$6 -> -10000 | D98: =-Допущения!$C$6 -> -10000 | E98: =-Допущения!$C$6 -> -10000 | F98: =-Допущения!$C$6 -> -10000 | G98: =-Допущения!$C$6 -> -10000 | H98: =-Допущения!$C$6 -> -10000 | I98: =-Допущения!$C$6 -> -10000 | ... M98: =-Допущения!$C$6 -> -10000

Sheet Допущения
A1: Допущения модели
A2: Синий — ввод; жёлтая заливка — ключевое допущение (проверить на пилоте). Цифры вне открытых данных — допущения команды.Все числа вне открытых данных — допущения команды (черновые, подбираем вместе).
A4: Параметр | B4: Ед. | C4: Пессимист | D4: База | E4: Оптимист | F4: Статус | G4: Источник / комментарий
A5: 1. Рамки кейса и финансовые параметры
A6: Лимит инвестиций (потолок, не цель) | B6: млн ₽ | C6: 10000 | D6: 10000 | E6: 10000 | F6: Факт кейса | G6: Кейс: до 10 млрд ₽ на 3 года.
A7: Максимальный срок окупаемости | B7: кварталов | C7: 12 | D7: 12 | E7: 12 | F7: Факт кейса | G7: Кейс: окупаемость до 3 лет.
A8: Ставка дисконтирования (годовая) | B8: % год | C8: 0.15 | D8: 0.15 | E8: 0.15 | F8: Допущение команды | G8: Ключевая ставка ЦБ 14% + 1 п.п.
A9: Маржа инкрементального дохода (после переменных издержек сделок) | B9: % | C9: 0.85 | D9: 0.85 | E9: 0.85 | F9: Допущение команды | G9: Доля выручки после переменных издержек. Без налогов.
A10: 2. Рынок и стартовая база
A11: Товарные сделки на платформе в год (база 2026) | B11: млн шт. | C11: 200 | D11: 200 | E11: 200 | F11: Открытые данные | G11: Forbes, А. Гевлич (2023): более 200 млн.
A12: Рост числа товарных сделок в год | B12: % год | C12: 0.03 | D12: 0.07 | E12: 0.1 | F12: Допущение команды | G12: Заказы с Доставкой в 2025: +30% (Retail.ru).
A13: Доля товарных сделок с Авито Доставкой (2026) | B13: % | C13: 0.37 | D13: 0.4 | E13: 0.43 | F13: Открытые данные | G13: МойСклад/Авито: 27% (I пол. 2024) → 37% (I пол. 2025).
A14: Рост доли Доставки в год | B14: п.п./год | C14: 0 | D14: 0.03 | E14: 0.04 | F14: Допущение команды | G14: В 2025 к 2024: +10 п.п.; берём 0–4.
A15: Месячная аудитория Авито | B15: млн чел. | C15: 51 | D15: 51 | E15: 51 | F15: Факт кейса | G15: Кейс: более 51 млн (сентябрь 2026). Без роста.
A16: 3. Охват механики
A17: Доля сделок Доставки в охваченных категориях — Год 1 | B17: % | C17: 0.21 | D17: 0.31 | E17: 0.39 | F17: Открытые данные | G17: Доли категорий в заказах с Доставкой (2025): хобби 15%, запчасти 10%, красота 8%, спорт 6%. Пессимист: хобби+спорт; база: +запчасти; оптимист: +красота.
A18: то же — Год 2 | B18: % | C18: 0.28 | D18: 0.55 | E18: 0.62 | F18: Допущение команды | G18: Расширение на соседние категории.
A19: то же — Год 3 | B19: % | C19: 0.35 | D19: 0.7 | E19: 0.78 | F19: Допущение команды | G19: Пессимист: без расширения.
A20: Доля сделок, идущих через карточки с блоком опыта (на зрелости) | B20: % | C20: 0.35 | D20: 0.45 | E20: 0.55 | F20: Допущение команды | G20: Блок виден только там, где набрано достаточно отзывов.
A21: 4. Воронка отзывов
A22: Доля подтверждённых покупателей, оставивших отзыв о модели (на зрелости) | B22: % | C22: 0.05 | D22: 0.08 | E22: 0.1 | F22: Допущение команды | G22: Авито (2024): после покупки товаров отзыв оставляют >23%, услуг >17%. Отзыв о модели сложнее.
A23: Доля авторов, обновивших отзыв позже / с долгим сроком использования | B23: % | C23: 0.15 | D23: 0.25 | E23: 0.35 | F23: Допущение команды | G23: Они же — аудитория пуша «оцените и продайте».
A24: Срок использования до пуша «оцените и продайте» | B24: кварталов | C24: 2 | D24: 2 | E24: 2 | F24: Допущение команды | G24: 2 кв. ≈ 6 мес.
A25: Доля обновивших отзыв, выставивших вещь через «Можно продать» | B25: % | C25: 0.05 | D25: 0.08 | E25: 0.12 | F25: Допущение команды | G25: Проверить на пилоте.
A26: Доля выставивших вещь, купивших продвижение | B26: % | C26: 0.12 | D26: 0.18 | E26: 0.25 | F26: Допущение команды
A27: Средний платёж за продвижение | B27: ₽ | C27: 150 | D27: 200 | E27: 250 | F27: Допущение команды
A28: Доля выставленных вещей, проданных через Доставку | B28: % | C28: 0.2 | D28: 0.3 | E28: 0.4 | F28: Допущение команды | G28: Доля новых объявлений, дошедших до сделки через Доставку.
A29: 5. Конверсия и доход со сделки
A30: Прирост конверсии в сделку в карточках с блоком (относительный) | B30: % | C30: 0.04 | D30: 0.05 | E30: 0.08 | F30: Оценка по бенчмарку | G30: Вилка 3–7% из данных Авито о видео, см. лист «Обоснование_uplift». Проверить A/B-тестом.
A31: Доля прироста, действительно инкрементальная | B31: % | C31: 0.65 | D31: 0.75 | E31: 0.85 | F31: Допущение команды | G31: За вычетом перетока сделок из других объявлений.
A32: Негативный эффект: потеря сделок в охваченных карточках (слабые модели, меньше контактов) | B32: % | C32: 0.005 | D32: 0.003 | E32: 0.0015 | F32: Допущение команды | G32: Риск: слабые модели теряют спрос, покупатели реже пишут продавцу. Контроль — контакты.
A33: Средний чек сделки с Доставкой | B33: ₽ | C33: 2000 | D33: 2000 | E33: 2000 | F33: Со слов команды (созвон) | G33: Созвон: около 2 000 ₽.
A34: Доход Авито с оборота сделки через Доставку | B34: % | C34: 0.1125 | D34: 0.125 | E34: 0.125 | F34: Со слов команды (созвон) | G34: Созвон: комиссия около 250 ₽ (12,5% чека). Пессимист — 225 ₽.
A35: Индексация среднего чека и комиссии в год (сложный процент) | B35: % год | C35: 0.04 | D35: 0.06 | E35: 0.07 | F35: Допущение команды | G35: Рост чека и комиссии со 2-го года: (1+i)^(год−1).
A36: 6. Визиты (эффект 3)
A37: Доля аудитории охваченных категорий, пользующаяся блоком в месяц (на зрелости) | B37: % | C37: 0.12 | D37: 0.15 | E37: 0.2 | F37: Допущение команды | G37: Читатели, авторы, участники обсуждений.
A38: Дополнительных визитов на участника в месяц | B38: визитов | C38: 0.5 | D38: 0.8 | E38: 1.1 | F38: Допущение команды | G38: Только новые визиты.
A39: Просмотров за дополнительный визит | B39: шт. | C39: 8 | D39: 10 | E39: 12 | F39: Допущение команды
A40: Доход от рекламы и рекомендаций на один просмотр | B40: ₽ | C40: 0.05 | D40: 0.08 | E40: 0.11 | F40: Допущение команды | G40: 40–120 ₽ за 1000 просмотров.
A41: 7. Удержание (эффект 4 — верхний сценарий)
A42: Доп. сделок в год на участника за счёт удержания (по всей платформе) | B42: сделок/год | C42: 0 | D42: 0 | E42: 0.04 | F42: Допущение команды | G42: Только в оптимисте.
A43: Средний доход Авито со сделки на платформе | B43: ₽ | C43: 150 | D43: 200 | E43: 250 | F43: Допущение команды | G43: Вся платформа; для эффекта 4.
A44: 8. Команда разработки (постоянные затраты)
A45: Роль (база, FTE) | B45: Ед. | C45: Год 1 | D45: Год 2 | E45: Год 3
A46: Продакт-менеджер | B46: FTE | C46: 1 | D46: 1 | E46: 1 | G46: Численность — допущение.
A47: Дизайнер | B47: FTE | C47: 1 | D47: 1 | E47: 2
A48: Бэкенд-разработчики | B48: FTE | C48: 3 | D48: 4 | E48: 4
A49: Фронтенд-разработчик | B49: FTE | C49: 1 | D49: 2 | E49: 2
A50: Мобильная разработка (iOS/Android) | B50: FTE | C50: 3 | D50: 4 | E50: 4
A51: ML-инженеры (ИИ-пересказ, модерация) | B51: FTE | C51: 2 | D51: 3 | E51: 3
A52: Аналитики | B52: FTE | C52: 2 | D52: 2 | E52: 2
A53: QA | B53: FTE | C53: 2 | D53: 2 | E53: 2
A54: Итого FTE (база) | B54: FTE | C54: =SUM(C46:C53) -> 15 | D54: =SUM(D46:D53) -> 19 | E54: =SUM(E46:E53) -> 20
A56: Команда — сценарные параметры
A57: Коэффициент к численности команды | B57: x | C57: 1 | D57: 0.85 | E57: 1 | F57: Допущение команды | G57: Компоненты Авито уже есть (кейс), поэтому в базе команда меньше. Пессимист: полная.
A58: Стоимость 1 FTE в месяц (с налогами и накладными) | B58: тыс. ₽ | C58: 450 | D58: 450 | E58: 450 | F58: Допущение команды | G58: Уточнить у HR.
A59: Индексация ФОТ в год | B59: % год | C59: 0.08 | D59: 0.08 | E59: 0.08 | F59: Допущение команды
A60: 9. Модерация, ИИ и мотивация авторов (переменные затраты)
A61: Сообщений в обсуждениях на один отзыв | B61: шт. | C61: 2 | D61: 2 | E61: 2 | F61: Допущение команды | G61: Модерация отзывов и сообщений.
A62: Стоимость ИИ-модерации одного объекта | B62: ₽ | C62: 1 | D62: 1 | E62: 1 | F62: Допущение команды | G62: Модели Авито (A-Vibe, A-Vision).
A63: Доля спорных объектов (ручная проверка) | B63: % | C63: 0.06 | D63: 0.04 | E63: 0.03 | F63: Допущение команды
A64: Стоимость ручной проверки | B64: ₽ | C64: 20 | D64: 20 | E64: 20 | F64: Допущение команды
A65: ИИ: генерация пересказов и ИИ-ответов, на 1 отзыв | B65: ₽ | C65: 2 | D65: 2 | E65: 2 | F65: Допущение команды
A66: Инфраструктура и хранение (фикс.) в квартал | B66: млн ₽ | C66: 2.5 | D66: 2.5 | E66: 3 | F66: Допущение команды
A67: Первый квартал инфраструктурных затрат | B67: № кв. | C67: 2 | D67: 2 | E67: 2 | F67: Допущение команды | G67: Альфа.
A68: Доля отзывов, получающих бонус/пожертвование | B68: % | C68: 0.5 | D68: 0.5 | E68: 0.5 | F68: Допущение команды | G68: Только за полезные отзывы.
A69: Сумма бонуса/пожертвования за отзыв | B69: ₽ | C69: 40 | D69: 25 | E69: 25 | F69: Допущение команды | G69: Открыто: бонусы или пожертвование.
A70: Годовой потолок бюджета на мотивацию | B70: млн ₽/год | C70: 150 | D70: 150 | E70: 200 | F70: Допущение команды | G70: В квартал — 1/4 лимита.
A71: Резерв на непредвиденные затраты | B71: % | C71: 0.1 | D71: 0.1 | E71: 0.1 | F71: Допущение команды
A72: 10. Маркетинг запуска
A73: Разовый маркетинг запуска | B73: млн ₽ | C73: 60 | D73: 50 | E73: 80 | F73: Допущение команды | G73: Внутренние каналы почти бесплатны; бюджет — на внешние активности и тесты.
A74: Первый квартал маркетинга запуска | B74: № кв. | C74: 3 | D74: 3 | E74: 3 | F74: Допущение команды
A75: Последний квартал маркетинга запуска | B75: № кв. | C75: 4 | D75: 4 | E75: 4 | F75: Допущение команды
A76: Текущий маркетинг и тесты после запуска, в квартал | B76: млн ₽ | C76: 4 | D76: 4 | E76: 8 | F76: Допущение команды
A77: 11. Профиль зрелости запуска по кварталам (доля от «зрелого» уровня)
A78: Квартал | D78: Q1 | E78: Q2 | F78: Q3 | G78: Q1–Q2: разработка, альфа; Q3: пилот; с Q4: запуск. | H78: Q5 | I78: Q6 | J78: Q7 | K78: Q8 | L78: Q9 | M78: Q10 | N78: Q11 | O78: Q12
A79: Профиль зрелости — Пессимист | B79: % от зрелости | D79: 0 | E79: 0 | F79: 0.05 | G79: 0.1 | H79: 0.2 | I79: 0.3 | J79: 0.4 | K79: 0.5 | L79: 0.6 | M79: 0.7 | N79: 0.8 | O79: 0.9
A80: Профиль зрелости — База | B80: % от зрелости | D80: 0 | E80: 0 | F80: 0.12 | G80: 0.3 | H80: 0.48 | I80: 0.65 | J80: 0.8 | K80: 0.92 | L80: 1 | M80: 1 | N80: 1 | O80: 1
A81: Профиль зрелости — Оптимист | B81: % от зрелости | D81: 0 | E81: 0 | F81: 0.15 | G81: 0.35 | H81: 0.55 | I81: 0.75 | J81: 0.9 | K81: 1 | L81: 1 | M81: 1 | N81: 1 | O81: 1

Sheet Обоснование_uplift
A1: Обоснование прироста конверсии в сделку
A2: Прямых данных по механике нет. Вилка выводится из внутреннего ориентира Авито. Точное значение даст A/B-тест.
A4: Показатель | B4: Низ | C4: Середина | D4: Верх | E4: Источник
A5: Рост взаимодействий от видео в объявлениях | B5: 0.06 | C5: 0.08 | D5: 0.1 | E5: Авито (кейс): +6–10%.
A6: Доля прироста взаимодействий, доходящая до сделки | B6: 0.5 | C6: 0.6 | D6: 0.7 | E6: Допущение. Проверяется на пилоте.
A7: Прирост конверсии в сделку (1 × 2) | B7: =B5*B6 -> 0.03 | C7: =C5*C6 -> 0.048 | D7: =D5*D6 -> 0.07
A8: Надбавка: отзывы владельцев сильнее видео | B8: 0 | C8: 0 | D8: 0.01 | E8: Суждение: только для оптимиста, +1 п.п.
A9: Вилка с надбавкой | B9: =B7+B8 -> 0.03 | C9: =C7+C8 -> 0.048 | D9: =D7+D8 -> 0.08
A11: Принято в модели | B11: Пессимист | C11: База | D11: Оптимист
A12: Прирост конверсии (лист «Допущения») | B12: =Допущения!C30 -> 0.04 | C12: =Допущения!D30 -> 0.05 | D12: =Допущения!E30 -> 0.08
A13: Мин. прирост: простая окупаемость за 12 кв. | B13: =Модель_Пессимист!C135 -> 0.3881844 | C13: =Модель_База!C135 -> 0.060507692 | D13: =Модель_Оптимист!C135 -> 0.028531037
A14: Мин. прирост: дисконтированная окупаемость за 12 кв. | B14: =Модель_Пессимист!C134 -> 0.42694901 | C14: =Модель_База!C134 -> 0.064461692 | D14: =Модель_Оптимист!C134 -> 0.031061689
A15: Запас: принято − мин. (простая), п.п. | B15: =IF(ISNUMBER(B13),B12-B13,"н/д") -> -0.3481844 | C15: =IF(ISNUMBER(C13),C12-C13,"н/д") -> -0.010507692 | D15: =IF(ISNUMBER(D13),D12-D13,"н/д") -> 0.051468963
A17: Что не использовано как оценка
A18: Spiegel Research Center (2017): +190–380% при 5 отзывах против 0. Наблюдательные данные, выборка не раскрыта, эффект убывает.
A19: PowerReviews/1WorldSync: 74% читают Q&A, 24% подозрительнее без него. Опрос, числа по конверсии нет.
A20: Вывод: направление эффекта подтверждено, величина — нет. Порог окупаемости базы лежит внутри вилки, поэтому нужен A/B-тест (ноутбук ab_test.ipynb).

Sheet Модель_Пессимист
A1: Финмодель - сценарий: Пессимист
A2: Номер сценария на листе (1 = Пессимист, 2 = База, 3 = Оптимист) | C2: 1
A3: Сценарий | C3: =INDEX(Допущения!$C$4:$E$4,$C$2) -> Пессимист
A4: Деньги — млн ₽, объёмы — тыс. шт. за квартал. Допущения — с листа «Допущения».
A5: Квартал № | D5: 1 | E5: =D5+1 -> 2 | F5: =E5+1 -> 3 | G5: =F5+1 -> 4 | H5: =G5+1 -> 5 | I5: =H5+1 -> 6 | J5: =I5+1 -> 7 | K5: =J5+1 -> 8 | L5: =K5+1 -> 9 | ... O5: =N5+1 -> 12
A6: Год проекта | D6: =ROUNDUP(D5/4,0) -> 1 | E6: =ROUNDUP(E5/4,0) -> 1 | F6: =ROUNDUP(F5/4,0) -> 1 | G6: =ROUNDUP(G5/4,0) -> 1 | H6: =ROUNDUP(H5/4,0) -> 2 | I6: =ROUNDUP(I5/4,0) -> 2 | J6: =ROUNDUP(J5/4,0) -> 2 | K6: =ROUNDUP(K5/4,0) -> 2 | ... O6: =ROUNDUP(O5/4,0) -> 3 | Q6: 1 | R6: 2 | S6: 3
A7: Период | C7: Параметр | D7: ="Q"&(MOD(D5-1,4)+1)&" "&(2026+D6) -> Q1 2027 | E7: ="Q"&(MOD(E5-1,4)+1)&" "&(2026+E6) -> Q2 2027 | F7: ="Q"&(MOD(F5-1,4)+1)&" "&(2026+F6) -> Q3 2027 | G7: ="Q"&(MOD(G5-1,4)+1)&" "&(2026+G6) -> Q4 2027 | H7: ="Q"&(MOD(H5-1,4)+1)&" "&(2026+H6) -> Q1 2028 | I7: ="Q"&(MOD(I5-1,4)+1)&" "&(2026+I6) -> Q2 2028 | J7: ="Q"&(MOD(J5-1,4)+1)&" "&(2026+J6) -> Q3 2028 | K7: ="Q"&(MOD(K5-1,4)+1)&" "&(2026+K6) -> Q4 2028 | ... O7: ="Q"&(MOD(O5-1,4)+1)&" "&(2026+O6) -> Q4 2029 | Q7: 2027 | R7: 2028 | S7: 2029 | T7: Итого
A9: Параметры сценария (из листа «Допущения»)
A10: Лимит инвестиций (потолок, не цель) | B10: млн ₽ | C10: =INDEX(Допущения!$C$6:$E$6,$C$2) -> 10000
A11: Максимальный срок окупаемости | B11: кварталов | C11: =INDEX(Допущения!$C$7:$E$7,$C$2) -> 12
A12: Ставка дисконтирования (годовая) | B12: % год | C12: =INDEX(Допущения!$C$8:$E$8,$C$2) -> 0.15
A13: Маржа инкрементального дохода (после переменных издержек сделок) | B13: % | C13: =INDEX(Допущения!$C$9:$E$9,$C$2) -> 0.85
A14: Товарные сделки на платформе в год (база 2026) | B14: млн шт. | C14: =INDEX(Допущения!$C$11:$E$11,$C$2) -> 200
A15: Рост числа товарных сделок в год | B15: % год | C15: =INDEX(Допущения!$C$12:$E$12,$C$2) -> 0.03
A16: Доля товарных сделок с Авито Доставкой (2026) | B16: % | C16: =INDEX(Допущения!$C$13:$E$13,$C$2) -> 0.37
A17: Рост доли Доставки в год | B17: п.п./год | C17: =INDEX(Допущения!$C$14:$E$14,$C$2) -> 0
A18: Месячная аудитория Авито | B18: млн чел. | C18: =INDEX(Допущения!$C$15:$E$15,$C$2) -> 51
A19: Доля сделок Доставки в охваченных категориях — Год 1 | B19: % | C19: =INDEX(Допущения!$C$17:$E$17,$C$2) -> 0.21
A20: то же — Год 2 | B20: % | C20: =INDEX(Допущения!$C$18:$E$18,$C$2) -> 0.28
A21: то же — Год 3 | B21: % | C21: =INDEX(Допущения!$C$19:$E$19,$C$2) -> 0.35
A22: Доля сделок, идущих через карточки с блоком опыта (на зрелости) | B22: % | C22: =INDEX(Допущения!$C$20:$E$20,$C$2) -> 0.35
A23: Доля подтверждённых покупателей, оставивших отзыв о модели (на зрелости) | B23: % | C23: =INDEX(Допущения!$C$22:$E$22,$C$2) -> 0.05
A24: Доля авторов, обновивших отзыв позже / с долгим сроком использования | B24: % | C24: =INDEX(Допущения!$C$23:$E$23,$C$2) -> 0.15
A25: Срок использования до пуша «оцените и продайте» | B25: кварталов | C25: =INDEX(Допущения!$C$24:$E$24,$C$2) -> 2
A26: Доля обновивших отзыв, выставивших вещь через «Можно продать» | B26: % | C26: =INDEX(Допущения!$C$25:$E$25,$C$2) -> 0.05
A27: Доля выставивших вещь, купивших продвижение | B27: % | C27: =INDEX(Допущения!$C$26:$E$26,$C$2) -> 0.12
A28: Средний платёж за продвижение | B28: ₽ | C28: =INDEX(Допущения!$C$27:$E$27,$C$2) -> 150
A29: Доля выставленных вещей, проданных через Доставку | B29: % | C29: =INDEX(Допущения!$C$28:$E$28,$C$2) -> 0.2
A30: Прирост конверсии в сделку в карточках с блоком (относительный) | B30: % | C30: =INDEX(Допущения!$C$30:$E$30,$C$2) -> 0.04
A31: Негативный эффект: потеря сделок в охваченных карточках (слабые модели, меньше контактов) | B31: % | C31: =INDEX(Допущения!$C$32:$E$32,$C$2) -> 0.005
A32: Доля прироста, действительно инкрементальная | B32: % | C32: =INDEX(Допущения!$C$31:$E$31,$C$2) -> 0.65
A33: Средний чек сделки с Доставкой | B33: ₽ | C33: =INDEX(Допущения!$C$33:$E$33,$C$2) -> 2000
A34: Доход Авито с оборота сделки через Доставку | B34: % | C34: =INDEX(Допущения!$C$34:$E$34,$C$2) -> 0.1125
A35: Индексация среднего чека и комиссии в год (сложный процент) | B35: % год | C35: =INDEX(Допущения!$C$35:$E$35,$C$2) -> 0.04
A36: Доход Авито с одной сделки через Доставку | B36: ₽ | C36: =$C$33*$C$34 -> 225
A37: Доля аудитории охваченных категорий, пользующаяся блоком в месяц (на зрелости) | B37: % | C37: =INDEX(Допущения!$C$37:$E$37,$C$2) -> 0.12
A38: Дополнительных визитов на участника в месяц | B38: визитов | C38: =INDEX(Допущения!$C$38:$E$38,$C$2) -> 0.5
A39: Просмотров за дополнительный визит | B39: шт. | C39: =INDEX(Допущения!$C$39:$E$39,$C$2) -> 8
A40: Доход от рекламы и рекомендаций на один просмотр | B40: ₽ | C40: =INDEX(Допущения!$C$40:$E$40,$C$2) -> 0.05
A41: Доп. сделок в год на участника за счёт удержания (по всей платформе) | B41: сделок/год | C41: =INDEX(Допущения!$C$42:$E$42,$C$2) -> 0
A42: Средний доход Авито со сделки на платформе | B42: ₽ | C42: =INDEX(Допущения!$C$43:$E$43,$C$2) -> 150
A43: Численность команды, Год 1 | B43: FTE | C43: =Допущения!C54*INDEX(Допущения!$C$57:$E$57,$C$2) -> 15
A44: Численность команды, Год 2 | B44: FTE | C44: =Допущения!D54*INDEX(Допущения!$C$57:$E$57,$C$2) -> 19
A45: Численность команды, Год 3 | B45: FTE | C45: =Допущения!E54*INDEX(Допущения!$C$57:$E$57,$C$2) -> 20
A46: Стоимость 1 FTE в месяц (с налогами и накладными) | B46: тыс. ₽ | C46: =INDEX(Допущения!$C$58:$E$58,$C$2) -> 450
A47: Индексация ФОТ в год | B47: % год | C47: =INDEX(Допущения!$C$59:$E$59,$C$2) -> 0.08
A48: Сообщений в обсуждениях на один отзыв | B48: шт. | C48: =INDEX(Допущения!$C$61:$E$61,$C$2) -> 2
A49: Стоимость ИИ-модерации одного объекта | B49: ₽ | C49: =INDEX(Допущения!$C$62:$E$62,$C$2) -> 1
A50: Доля спорных объектов (ручная проверка) | B50: % | C50: =INDEX(Допущения!$C$63:$E$63,$C$2) -> 0.06
A51: Стоимость ручной проверки | B51: ₽ | C51: =INDEX(Допущения!$C$64:$E$64,$C$2) -> 20
A52: ИИ: генерация пересказов и ИИ-ответов, на 1 отзыв | B52: ₽ | C52: =INDEX(Допущения!$C$65:$E$65,$C$2) -> 2
A53: Инфраструктура и хранение (фикс.) в квартал | B53: млн ₽ | C53: =INDEX(Допущения!$C$66:$E$66,$C$2) -> 2.5
A54: Первый квартал инфраструктурных затрат | B54: № кв. | C54: =INDEX(Допущения!$C$67:$E$67,$C$2) -> 2
A55: Доля отзывов, получающих бонус/пожертвование | B55: % | C55: =INDEX(Допущения!$C$68:$E$68,$C$2) -> 0.5
A56: Сумма бонуса/пожертвования за отзыв | B56: ₽ | C56: =INDEX(Допущения!$C$69:$E$69,$C$2) -> 40
A57: Годовой потолок бюджета на мотивацию | B57: млн ₽/год | C57: =INDEX(Допущения!$C$70:$E$70,$C$2) -> 150
A58: Резерв на непредвиденные затраты | B58: % | C58: =INDEX(Допущения!$C$71:$E$71,$C$2) -> 0.1
A59: Разовый маркетинг запуска | B59: млн ₽ | C59: =INDEX(Допущения!$C$73:$E$73,$C$2) -> 60
A60: Первый квартал маркетинга запуска | B60: № кв. | C60: =INDEX(Допущения!$C$74:$E$74,$C$2) -> 3
A61: Последний квартал маркетинга запуска | B61: № кв. | C61: =INDEX(Допущения!$C$75:$E$75,$C$2) -> 4
A62: Текущий маркетинг и тесты после запуска, в квартал | B62: млн ₽ | C62: =INDEX(Допущения!$C$76:$E$76,$C$2) -> 4
A64: A. Объёмы и охват
A65: Товарные сделки на платформе | B65: тыс. шт. | D65: =$C$14*1000*(1+$C$15)^D$6/4 -> 51500 | E65: =$C$14*1000*(1+$C$15)^E$6/4 -> 51500 | F65: =$C$14*1000*(1+$C$15)^F$6/4 -> 51500 | G65: =$C$14*1000*(1+$C$15)^G$6/4 -> 51500 | H65: =$C$14*1000*(1+$C$15)^H$6/4 -> 53045 | I65: =$C$14*1000*(1+$C$15)^I$6/4 -> 53045 | J65: =$C$14*1000*(1+$C$15)^J$6/4 -> 53045 | K65: =$C$14*1000*(1+$C$15)^K$6/4 -> 53045 | ... O65: =$C$14*1000*(1+$C$15)^O$6/4 -> 54636.35 | Q65: =SUMIF($D$6:$O$6,Q$6,$D65:$O65) -> 206000 | R65: =SUMIF($D$6:$O$6,R$6,$D65:$O65) -> 212180 | S65: =SUMIF($D$6:$O$6,S$6,$D65:$O65) -> 218545.4 | T65: =SUM(Q65:S65) -> 636725.4
A66: Доля сделок через Доставку | B66: % | D66: =$C$16+$C$17*D$6 -> 0.37 | E66: =$C$16+$C$17*E$6 -> 0.37 | F66: =$C$16+$C$17*F$6 -> 0.37 | G66: =$C$16+$C$17*G$6 -> 0.37 | H66: =$C$16+$C$17*H$6 -> 0.37 | I66: =$C$16+$C$17*I$6 -> 0.37 | J66: =$C$16+$C$17*J$6 -> 0.37 | K66: =$C$16+$C$17*K$6 -> 0.37 | ... O66: =$C$16+$C$17*O$6 -> 0.37
A67: Сделки через Доставку | B67: тыс. шт. | D67: =D65*D66 -> 19055 | E67: =E65*E66 -> 19055 | F67: =F65*F66 -> 19055 | G67: =G65*G66 -> 19055 | H67: =H65*H66 -> 19626.65 | I67: =I65*I66 -> 19626.65 | J67: =J65*J66 -> 19626.65 | K67: =K65*K66 -> 19626.65 | ... O67: =O65*O66 -> 20215.449 | Q67: =SUMIF($D$6:$O$6,Q$6,$D67:$O67) -> 76220 | R67: =SUMIF($D$6:$O$6,R$6,$D67:$O67) -> 78506.6 | S67: =SUMIF($D$6:$O$6,S$6,$D67:$O67) -> 80861.798 | T67: =SUM(Q67:S67) -> 235588.4
A68: Охват категорий механикой (доля сделок Доставки) | B68: % | D68: =INDEX($C$19:$C$21,D$6) -> 0.21 | E68: =INDEX($C$19:$C$21,E$6) -> 0.21 | F68: =INDEX($C$19:$C$21,F$6) -> 0.21 | G68: =INDEX($C$19:$C$21,G$6) -> 0.21 | H68: =INDEX($C$19:$C$21,H$6) -> 0.28 | I68: =INDEX($C$19:$C$21,I$6) -> 0.28 | J68: =INDEX($C$19:$C$21,J$6) -> 0.28 | K68: =INDEX($C$19:$C$21,K$6) -> 0.28 | ... O68: =INDEX($C$19:$C$21,O$6) -> 0.35
A69: Профиль зрелости запуска | B69: % | D69: =INDEX(Допущения!D$79:D$81,$C$2) -> 0 | E69: =INDEX(Допущения!E$79:E$81,$C$2) -> 0 | F69: =INDEX(Допущения!F$79:F$81,$C$2) -> 0.05 | G69: =INDEX(Допущения!G$79:G$81,$C$2) -> 0.1 | H69: =INDEX(Допущения!H$79:H$81,$C$2) -> 0.2 | I69: =INDEX(Допущения!I$79:I$81,$C$2) -> 0.3 | J69: =INDEX(Допущения!J$79:J$81,$C$2) -> 0.4 | K69: =INDEX(Допущения!K$79:K$81,$C$2) -> 0.5 | ... O69: =INDEX(Допущения!O$79:O$81,$C$2) -> 0.9
A70: Сделки Доставки в охваченных категориях | B70: тыс. шт. | D70: =D67*D68 -> 4001.55 | E70: =E67*E68 -> 4001.55 | F70: =F67*F68 -> 4001.55 | G70: =G67*G68 -> 4001.55 | H70: =H67*H68 -> 5495.462 | I70: =I67*I68 -> 5495.462 | J70: =J67*J68 -> 5495.462 | K70: =K67*K68 -> 5495.462 | ... O70: =O67*O68 -> 7075.4073 | Q70: =SUMIF($D$6:$O$6,Q$6,$D70:$O70) -> 16006.2 | R70: =SUMIF($D$6:$O$6,R$6,$D70:$O70) -> 21981.848 | S70: =SUMIF($D$6:$O$6,S$6,$D70:$O70) -> 28301.629 | T70: =SUM(Q70:S70) -> 66289.677
A71: из них — в карточках с блоком опыта | B71: тыс. шт. | D71: =D70*$C$22*D69 -> 0 | E71: =E70*$C$22*E69 -> 0 | F71: =F70*$C$22*F69 -> 70.027125 | G71: =G70*$C$22*G69 -> 140.05425 | H71: =H70*$C$22*H69 -> 384.68234 | I71: =I70*$C$22*I69 -> 577.02351 | J71: =J70*$C$22*J69 -> 769.36468 | K71: =K70*$C$22*K69 -> 961.70585 | ... O71: =O70*$C$22*O69 -> 2228.7533 | Q71: =SUMIF($D$6:$O$6,Q$6,$D71:$O71) -> 210.08138 | R71: =SUMIF($D$6:$O$6,R$6,$D71:$O71) -> 2692.7764 | S71: =SUMIF($D$6:$O$6,S$6,$D71:$O71) -> 7429.1777 | T71: =SUM(Q71:S71) -> 10332.035
A73: B. Воронка отзывов
A74: Отзывы о моделях (подтверждённые покупатели) | B74: тыс. шт. | D74: =D70*D69*$C$23 -> 0 | E74: =E70*E69*$C$23 -> 0 | F74: =F70*F69*$C$23 -> 10.003875 | G74: =G70*G69*$C$23 -> 20.00775 | H74: =H70*H69*$C$23 -> 54.95462 | I74: =I70*I69*$C$23 -> 82.43193 | J74: =J70*J69*$C$23 -> 109.90924 | K74: =K70*K69*$C$23 -> 137.38655 | ... O74: =O70*O69*$C$23 -> 318.39333 | Q74: =SUMIF($D$6:$O$6,Q$6,$D74:$O74) -> 30.011625 | R74: =SUMIF($D$6:$O$6,R$6,$D74:$O74) -> 384.68234 | S74: =SUMIF($D$6:$O$6,S$6,$D74:$O74) -> 1061.3111 | T74: =SUM(Q74:S74) -> 1476.0051
A75: Авторы с долгим сроком использования / обновили отзыв | B75: тыс. шт. | D75: =IF(D$5>$C$25,INDEX($D$74:$O$74,D$5-$C$25),0)*$C$24 -> 0 | E75: =IF(E$5>$C$25,INDEX($D$74:$O$74,E$5-$C$25),0)*$C$24 -> 0 | F75: =IF(F$5>$C$25,INDEX($D$74:$O$74,F$5-$C$25),0)*$C$24 -> 0 | G75: =IF(G$5>$C$25,INDEX($D$74:$O$74,G$5-$C$25),0)*$C$24 -> 0 | H75: =IF(H$5>$C$25,INDEX($D$74:$O$74,H$5-$C$25),0)*$C$24 -> 1.5005812 | I75: =IF(I$5>$C$25,INDEX($D$74:$O$74,I$5-$C$25),0)*$C$24 -> 3.0011625 | J75: =IF(J$5>$C$25,INDEX($D$74:$O$74,J$5-$C$25),0)*$C$24 -> 8.243193 | K75: =IF(K$5>$C$25,INDEX($D$74:$O$74,K$5-$C$25),0)*$C$24 -> 12.36479 | ... O75: =IF(O$5>$C$25,INDEX($D$74:$O$74,O$5-$C$25),0)*$C$24 -> 37.145888 | Q75: =SUMIF($D$6:$O$6,Q$6,$D75:$O75) -> 0 | R75: =SUMIF($D$6:$O$6,R$6,$D75:$O75) -> 25.109726 | S75: =SUMIF($D$6:$O$6,S$6,$D75:$O75) -> 106.07959 | T75: =SUM(Q75:S75) -> 131.18932
A76: Выставили вещь через «Можно продать» | B76: тыс. шт. | D76: =D75*$C$26 -> 0 | E76: =E75*$C$26 -> 0 | F76: =F75*$C$26 -> 0 | G76: =G75*$C$26 -> 0 | H76: =H75*$C$26 -> 0.075029062 | I76: =I75*$C$26 -> 0.15005812 | J76: =J75*$C$26 -> 0.41215965 | K76: =K75*$C$26 -> 0.61823947 | ... O76: =O75*$C$26 -> 1.8572944 | Q76: =SUMIF($D$6:$O$6,Q$6,$D76:$O76) -> 0 | R76: =SUMIF($D$6:$O$6,R$6,$D76:$O76) -> 1.2554863 | S76: =SUMIF($D$6:$O$6,S$6,$D76:$O76) -> 5.3039795 | T76: =SUM(Q76:S76) -> 6.5594658
A77: Купили продвижение | B77: тыс. шт. | D77: =D76*$C$27 -> 0 | E77: =E76*$C$27 -> 0 | F77: =F76*$C$27 -> 0 | G77: =G76*$C$27 -> 0 | H77: =H76*$C$27 -> 0.0090034875 | I77: =I76*$C$27 -> 0.018006975 | J77: =J76*$C$27 -> 0.049459158 | K77: =K76*$C$27 -> 0.074188737 | ... O77: =O76*$C$27 -> 0.22287533 | Q77: =SUMIF($D$6:$O$6,Q$6,$D77:$O77) -> 0 | R77: =SUMIF($D$6:$O$6,R$6,$D77:$O77) -> 0.15065836 | S77: =SUMIF($D$6:$O$6,S$6,$D77:$O77) -> 0.63647754 | T77: =SUM(Q77:S77) -> 0.7871359
A79: C. Эффекты (дополнительная выручка Авито)
A80: Доход Авито с одной сделки через Доставку (с индексацией) | B80: ₽ | D80: =$C$36*(1+$C$35)^(D$6-1) -> 225 | E80: =$C$36*(1+$C$35)^(E$6-1) -> 225 | F80: =$C$36*(1+$C$35)^(F$6-1) -> 225 | G80: =$C$36*(1+$C$35)^(G$6-1) -> 225 | H80: =$C$36*(1+$C$35)^(H$6-1) -> 234 | I80: =$C$36*(1+$C$35)^(I$6-1) -> 234 | J80: =$C$36*(1+$C$35)^(J$6-1) -> 234 | K80: =$C$36*(1+$C$35)^(K$6-1) -> 234 | ... O80: =$C$36*(1+$C$35)^(O$6-1) -> 243.36 | Q80: =AVERAGEIF($D$6:$O$6,Q$6,$D80:$O80) -> 225 | R80: =AVERAGEIF($D$6:$O$6,R$6,$D80:$O80) -> 234 | S80: =AVERAGEIF($D$6:$O$6,S$6,$D80:$O80) -> 243.36
A81: Эффект 1: прирост сделок (инкрементальный) | B81: тыс. шт. | D81: =D71*$C$30*$C$32 -> 0 | E81: =E71*$C$30*$C$32 -> 0 | F81: =F71*$C$30*$C$32 -> 1.8207053 | G81: =G71*$C$30*$C$32 -> 3.6414105 | H81: =H71*$C$30*$C$32 -> 10.001741 | I81: =I71*$C$30*$C$32 -> 15.002611 | J81: =J71*$C$30*$C$32 -> 20.003482 | K81: =K71*$C$30*$C$32 -> 25.004352 | ... O81: =O71*$C$30*$C$32 -> 57.947586 | Q81: =SUMIF($D$6:$O$6,Q$6,$D81:$O81) -> 5.4621157 | R81: =SUMIF($D$6:$O$6,R$6,$D81:$O81) -> 70.012186 | S81: =SUMIF($D$6:$O$6,S$6,$D81:$O81) -> 193.15862 | T81: =SUM(Q81:S81) -> 268.63292
A82: Эффект 1: потеря сделок (слабые модели, меньше контактов) | B82: тыс. шт. | D82: =D71*$C$31 -> 0 | E82: =E71*$C$31 -> 0 | F82: =F71*$C$31 -> 0.35013563 | G82: =G71*$C$31 -> 0.70027125 | H82: =H71*$C$31 -> 1.9234117 | I82: =I71*$C$31 -> 2.8851175 | J82: =J71*$C$31 -> 3.8468234 | K82: =K71*$C$31 -> 4.8085293 | ... O82: =O71*$C$31 -> 11.143767 | Q82: =SUMIF($D$6:$O$6,Q$6,$D82:$O82) -> 1.0504069 | R82: =SUMIF($D$6:$O$6,R$6,$D82:$O82) -> 13.463882 | S82: =SUMIF($D$6:$O$6,S$6,$D82:$O82) -> 37.145888 | T82: =SUM(Q82:S82) -> 51.660177
A83: Эффект 1: чистый прирост сделок | B83: тыс. шт. | D83: =D81-D82 -> 0 | E83: =E81-E82 -> 0 | F83: =F81-F82 -> 1.4705696 | G83: =G81-G82 -> 2.9411392 | H83: =H81-H82 -> 8.0783291 | I83: =I81-I82 -> 12.117494 | J83: =J81-J82 -> 16.156658 | K83: =K81-K82 -> 20.195823 | ... O83: =O81-O82 -> 46.803819 | Q83: =SUMIF($D$6:$O$6,Q$6,$D83:$O83) -> 4.4117089 | R83: =SUMIF($D$6:$O$6,R$6,$D83:$O83) -> 56.548304 | S83: =SUMIF($D$6:$O$6,S$6,$D83:$O83) -> 156.01273 | T83: =SUM(Q83:S83) -> 216.97274
A84: Эффект 1: доход от конверсии (комиссия Доставки) | B84: млн ₽ | D84: =D83*D80/1000 -> 0 | E84: =E83*E80/1000 -> 0 | F84: =F83*F80/1000 -> 0.33087817 | G84: =G83*G80/1000 -> 0.66175633 | H84: =H83*H80/1000 -> 1.890329 | I84: =I83*I80/1000 -> 2.8354935 | J84: =J83*J80/1000 -> 3.780658 | K84: =K83*K80/1000 -> 4.7258225 | ... O84: =O83*O80/1000 -> 11.390178 | Q84: =SUMIF($D$6:$O$6,Q$6,$D84:$O84) -> 0.9926345 | R84: =SUMIF($D$6:$O$6,R$6,$D84:$O84) -> 13.232303 | S84: =SUMIF($D$6:$O$6,S$6,$D84:$O84) -> 37.967258 | T84: =SUM(Q84:S84) -> 52.192196
A85: Эффект 2: доход от продвижения новых объявлений | B85: млн ₽ | D85: =D77*$C$28/1000 -> 0 | E85: =E77*$C$28/1000 -> 0 | F85: =F77*$C$28/1000 -> 0 | G85: =G77*$C$28/1000 -> 0 | H85: =H77*$C$28/1000 -> 0.0013505231 | I85: =I77*$C$28/1000 -> 0.0027010462 | J85: =J77*$C$28/1000 -> 0.0074188737 | K85: =K77*$C$28/1000 -> 0.011128311 | ... O85: =O77*$C$28/1000 -> 0.0334313 | Q85: =SUMIF($D$6:$O$6,Q$6,$D85:$O85) -> 0 | R85: =SUMIF($D$6:$O$6,R$6,$D85:$O85) -> 0.022598754 | S85: =SUMIF($D$6:$O$6,S$6,$D85:$O85) -> 0.095471631 | T85: =SUM(Q85:S85) -> 0.11807038
A86: Эффект 2: доход со сделок по новым объявлениям | B86: млн ₽ | D86: =D76*$C$29*D80/1000 -> 0 | E86: =E76*$C$29*E80/1000 -> 0 | F86: =F76*$C$29*F80/1000 -> 0 | G86: =G76*$C$29*G80/1000 -> 0 | H86: =H76*$C$29*H80/1000 -> 0.0035113601 | I86: =I76*$C$29*I80/1000 -> 0.0070227203 | J86: =J76*$C$29*J80/1000 -> 0.019289072 | K86: =K76*$C$29*K80/1000 -> 0.028933607 | ... O86: =O76*$C$29*O80/1000 -> 0.090398234 | Q86: =SUMIF($D$6:$O$6,Q$6,$D86:$O86) -> 0 | R86: =SUMIF($D$6:$O$6,R$6,$D86:$O86) -> 0.058756759 | S86: =SUMIF($D$6:$O$6,S$6,$D86:$O86) -> 0.25815529 | T86: =SUM(Q86:S86) -> 0.31691205
A87: Участники блока в месяц (аудитория) | B87: тыс. чел. | D87: =$C$18*1000*D68*$C$37*D69 -> 0 | E87: =$C$18*1000*E68*$C$37*E69 -> 0 | F87: =$C$18*1000*F68*$C$37*F69 -> 64.26 | G87: =$C$18*1000*G68*$C$37*G69 -> 128.52 | H87: =$C$18*1000*H68*$C$37*H69 -> 342.72 | I87: =$C$18*1000*I68*$C$37*I69 -> 514.08 | J87: =$C$18*1000*J68*$C$37*J69 -> 685.44 | K87: =$C$18*1000*K68*$C$37*K69 -> 856.8 | ... O87: =$C$18*1000*O68*$C$37*O69 -> 1927.8 | Q87: =AVERAGEIF($D$6:$O$6,Q$6,$D87:$O87) -> 48.195 | R87: =AVERAGEIF($D$6:$O$6,R$6,$D87:$O87) -> 599.76 | S87: =AVERAGEIF($D$6:$O$6,S$6,$D87:$O87) -> 1606.5
A88: Эффект 3: дополнительные просмотры за квартал | B88: тыс. шт. | D88: =D87*$C$38*3*$C$39 -> 0 | E88: =E87*$C$38*3*$C$39 -> 0 | F88: =F87*$C$38*3*$C$39 -> 771.12 | G88: =G87*$C$38*3*$C$39 -> 1542.24 | H88: =H87*$C$38*3*$C$39 -> 4112.64 | I88: =I87*$C$38*3*$C$39 -> 6168.96 | J88: =J87*$C$38*3*$C$39 -> 8225.28 | K88: =K87*$C$38*3*$C$39 -> 10281.6 | ... O88: =O87*$C$38*3*$C$39 -> 23133.6 | Q88: =SUMIF($D$6:$O$6,Q$6,$D88:$O88) -> 2313.36 | R88: =SUMIF($D$6:$O$6,R$6,$D88:$O88) -> 28788.48 | S88: =SUMIF($D$6:$O$6,S$6,$D88:$O88) -> 77112 | T88: =SUM(Q88:S88) -> 108213.84
A89: Эффект 3: доход от рекламы и рекомендаций | B89: млн ₽ | D89: =D88*$C$40/1000 -> 0 | E89: =E88*$C$40/1000 -> 0 | F89: =F88*$C$40/1000 -> 0.038556 | G89: =G88*$C$40/1000 -> 0.077112 | H89: =H88*$C$40/1000 -> 0.205632 | I89: =I88*$C$40/1000 -> 0.308448 | J89: =J88*$C$40/1000 -> 0.411264 | K89: =K88*$C$40/1000 -> 0.51408 | ... O89: =O88*$C$40/1000 -> 1.15668 | Q89: =SUMIF($D$6:$O$6,Q$6,$D89:$O89) -> 0.115668 | R89: =SUMIF($D$6:$O$6,R$6,$D89:$O89) -> 1.439424 | S89: =SUMIF($D$6:$O$6,S$6,$D89:$O89) -> 3.8556 | T89: =SUM(Q89:S89) -> 5.410692
A90: Эффект 4: удержание (верхний сценарий) | B90: млн ₽ | D90: =D87*$C$41/4*$C$42/1000 -> 0 | E90: =E87*$C$41/4*$C$42/1000 -> 0 | F90: =F87*$C$41/4*$C$42/1000 -> 0 | G90: =G87*$C$41/4*$C$42/1000 -> 0 | H90: =H87*$C$41/4*$C$42/1000 -> 0 | I90: =I87*$C$41/4*$C$42/1000 -> 0 | J90: =J87*$C$41/4*$C$42/1000 -> 0 | K90: =K87*$C$41/4*$C$42/1000 -> 0 | ... O90: =O87*$C$41/4*$C$42/1000 -> 0 | Q90: =SUMIF($D$6:$O$6,Q$6,$D90:$O90) -> 0 | R90: =SUMIF($D$6:$O$6,R$6,$D90:$O90) -> 0 | S90: =SUMIF($D$6:$O$6,S$6,$D90:$O90) -> 0 | T90: =SUM(Q90:S90) -> 0
A91: Дополнительная выручка всего | B91: млн ₽ | D91: =D84+D85+D86+D89+D90 -> 0 | E91: =E84+E85+E86+E89+E90 -> 0 | F91: =F84+F85+F86+F89+F90 -> 0.36943417 | G91: =G84+G85+G86+G89+G90 -> 0.73886833 | H91: =H84+H85+H86+H89+H90 -> 2.1008229 | I91: =I84+I85+I86+I89+I90 -> 3.1536653 | J91: =J84+J85+J86+J89+J90 -> 4.21863 | K91: =K84+K85+K86+K89+K90 -> 5.2799645 | ... O91: =O84+O85+O86+O89+O90 -> 12.670687 | Q91: =SUMIF($D$6:$O$6,Q$6,$D91:$O91) -> 1.1083025 | R91: =SUMIF($D$6:$O$6,R$6,$D91:$O91) -> 14.753083 | S91: =SUMIF($D$6:$O$6,S$6,$D91:$O91) -> 42.176485 | T91: =SUM(Q91:S91) -> 58.03787
A92: Маржинальный доход (после переменных издержек) | B92: млн ₽ | D92: =D91*$C$13 -> 0 | E92: =E91*$C$13 -> 0 | F92: =F91*$C$13 -> 0.31401904 | G92: =G91*$C$13 -> 0.62803808 | H92: =H91*$C$13 -> 1.7856995 | I92: =I91*$C$13 -> 2.6806155 | J92: =J91*$C$13 -> 3.5858355 | K92: =K91*$C$13 -> 4.4879698 | ... O92: =O91*$C$13 -> 10.770084 | Q92: =SUMIF($D$6:$O$6,Q$6,$D92:$O92) -> 0.94205712 | R92: =SUMIF($D$6:$O$6,R$6,$D92:$O92) -> 12.54012 | S92: =SUMIF($D$6:$O$6,S$6,$D92:$O92) -> 35.850012 | T92: =SUM(Q92:S92) -> 49.33219
A94: D. Затраты
A95: Численность команды | B95: FTE | D95: =INDEX($C$43:$C$45,D$6) -> 15 | E95: =INDEX($C$43:$C$45,E$6) -> 15 | F95: =INDEX($C$43:$C$45,F$6) -> 15 | G95: =INDEX($C$43:$C$45,G$6) -> 15 | H95: =INDEX($C$43:$C$45,H$6) -> 19 | I95: =INDEX($C$43:$C$45,I$6) -> 19 | J95: =INDEX($C$43:$C$45,J$6) -> 19 | K95: =INDEX($C$43:$C$45,K$6) -> 19 | ... O95: =INDEX($C$43:$C$45,O$6) -> 20 | Q95: =AVERAGEIF($D$6:$O$6,Q$6,$D95:$O95) -> 15 | R95: =AVERAGEIF($D$6:$O$6,R$6,$D95:$O95) -> 19 | S95: =AVERAGEIF($D$6:$O$6,S$6,$D95:$O95) -> 20
A96: Команда разработки | B96: млн ₽ | D96: =D95*$C$46*3*(1+$C$47)^(D$6-1)/1000 -> 20.25 | E96: =E95*$C$46*3*(1+$C$47)^(E$6-1)/1000 -> 20.25 | F96: =F95*$C$46*3*(1+$C$47)^(F$6-1)/1000 -> 20.25 | G96: =G95*$C$46*3*(1+$C$47)^(G$6-1)/1000 -> 20.25 | H96: =H95*$C$46*3*(1+$C$47)^(H$6-1)/1000 -> 27.702 | I96: =I95*$C$46*3*(1+$C$47)^(I$6-1)/1000 -> 27.702 | J96: =J95*$C$46*3*(1+$C$47)^(J$6-1)/1000 -> 27.702 | K96: =K95*$C$46*3*(1+$C$47)^(K$6-1)/1000 -> 27.702 | ... O96: =O95*$C$46*3*(1+$C$47)^(O$6-1)/1000 -> 31.4928 | Q96: =SUMIF($D$6:$O$6,Q$6,$D96:$O96) -> 81 | R96: =SUMIF($D$6:$O$6,R$6,$D96:$O96) -> 110.808 | S96: =SUMIF($D$6:$O$6,S$6,$D96:$O96) -> 125.9712 | T96: =SUM(Q96:S96) -> 317.7792
A97: Объекты модерации (отзывы + сообщения) | B97: тыс. шт. | D97: =D74*(1+$C$48) -> 0 | E97: =E74*(1+$C$48) -> 0 | F97: =F74*(1+$C$48) -> 30.011625 | G97: =G74*(1+$C$48) -> 60.02325 | H97: =H74*(1+$C$48) -> 164.86386 | I97: =I74*(1+$C$48) -> 247.29579 | J97: =J74*(1+$C$48) -> 329.72772 | K97: =K74*(1+$C$48) -> 412.15965 | ... O97: =O74*(1+$C$48) -> 955.17999 | Q97: =SUMIF($D$6:$O$6,Q$6,$D97:$O97) -> 90.034875 | R97: =SUMIF($D$6:$O$6,R$6,$D97:$O97) -> 1154.047 | S97: =SUMIF($D$6:$O$6,S$6,$D97:$O97) -> 3183.9333 | T97: =SUM(Q97:S97) -> 4428.0152
A98: ИИ-модерация | B98: млн ₽ | D98: =D97*$C$49/1000 -> 0 | E98: =E97*$C$49/1000 -> 0 | F98: =F97*$C$49/1000 -> 0.030011625 | G98: =G97*$C$49/1000 -> 0.06002325 | H98: =H97*$C$49/1000 -> 0.16486386 | I98: =I97*$C$49/1000 -> 0.24729579 | J98: =J97*$C$49/1000 -> 0.32972772 | K98: =K97*$C$49/1000 -> 0.41215965 | ... O98: =O97*$C$49/1000 -> 0.95517999 | Q98: =SUMIF($D$6:$O$6,Q$6,$D98:$O98) -> 0.090034875 | R98: =SUMIF($D$6:$O$6,R$6,$D98:$O98) -> 1.154047 | S98: =SUMIF($D$6:$O$6,S$6,$D98:$O98) -> 3.1839333 | T98: =SUM(Q98:S98) -> 4.4280152
A99: Ручная модерация спорных случаев | B99: млн ₽ | D99: =D97*$C$50*$C$51/1000 -> 0 | E99: =E97*$C$50*$C$51/1000 -> 0 | F99: =F97*$C$50*$C$51/1000 -> 0.03601395 | G99: =G97*$C$50*$C$51/1000 -> 0.0720279 | H99: =H97*$C$50*$C$51/1000 -> 0.19783663 | I99: =I97*$C$50*$C$51/1000 -> 0.29675495 | J99: =J97*$C$50*$C$51/1000 -> 0.39567326 | K99: =K97*$C$50*$C$51/1000 -> 0.49459158 | ... O99: =O97*$C$50*$C$51/1000 -> 1.146216 | Q99: =SUMIF($D$6:$O$6,Q$6,$D99:$O99) -> 0.10804185 | R99: =SUMIF($D$6:$O$6,R$6,$D99:$O99) -> 1.3848564 | S99: =SUMIF($D$6:$O$6,S$6,$D99:$O99) -> 3.82072 | T99: =SUM(Q99:S99) -> 5.3136182
A100: ИИ и инфраструктура | B100: млн ₽ | D100: =D74*$C$52/1000+IF(D$5>=$C$54,$C$53,0) -> 0 | E100: =E74*$C$52/1000+IF(E$5>=$C$54,$C$53,0) -> 2.5 | F100: =F74*$C$52/1000+IF(F$5>=$C$54,$C$53,0) -> 2.5200077 | G100: =G74*$C$52/1000+IF(G$5>=$C$54,$C$53,0) -> 2.5400155 | H100: =H74*$C$52/1000+IF(H$5>=$C$54,$C$53,0) -> 2.6099092 | I100: =I74*$C$52/1000+IF(I$5>=$C$54,$C$53,0) -> 2.6648639 | J100: =J74*$C$52/1000+IF(J$5>=$C$54,$C$53,0) -> 2.7198185 | K100: =K74*$C$52/1000+IF(K$5>=$C$54,$C$53,0) -> 2.7747731 | ... O100: =O74*$C$52/1000+IF(O$5>=$C$54,$C$53,0) -> 3.1367867 | Q100: =SUMIF($D$6:$O$6,Q$6,$D100:$O100) -> 7.5600233 | R100: =SUMIF($D$6:$O$6,R$6,$D100:$O100) -> 10.769365 | S100: =SUMIF($D$6:$O$6,S$6,$D100:$O100) -> 12.122622 | T100: =SUM(Q100:S100) -> 30.45201
A101: Мотивация авторов (с годовым потолком) | B101: млн ₽ | D101: =MIN(D74*$C$55*$C$56/1000,$C$57/4) -> 0 | E101: =MIN(E74*$C$55*$C$56/1000,$C$57/4) -> 0 | F101: =MIN(F74*$C$55*$C$56/1000,$C$57/4) -> 0.2000775 | G101: =MIN(G74*$C$55*$C$56/1000,$C$57/4) -> 0.400155 | H101: =MIN(H74*$C$55*$C$56/1000,$C$57/4) -> 1.0990924 | I101: =MIN(I74*$C$55*$C$56/1000,$C$57/4) -> 1.6486386 | J101: =MIN(J74*$C$55*$C$56/1000,$C$57/4) -> 2.1981848 | K101: =MIN(K74*$C$55*$C$56/1000,$C$57/4) -> 2.747731 | ... O101: =MIN(O74*$C$55*$C$56/1000,$C$57/4) -> 6.3678666 | Q101: =SUMIF($D$6:$O$6,Q$6,$D101:$O101) -> 0.6002325 | R101: =SUMIF($D$6:$O$6,R$6,$D101:$O101) -> 7.6936468 | S101: =SUMIF($D$6:$O$6,S$6,$D101:$O101) -> 21.226222 | T101: =SUM(Q101:S101) -> 29.520101
A102: Маркетинг (запуск + текущий) | B102: млн ₽ | D102: =IF(AND(D$5>=$C$60,D$5<=$C$61),$C$59/($C$61-$C$60+1),0)+IF(D$5>$C$61,$C$62,0) -> 0 | E102: =IF(AND(E$5>=$C$60,E$5<=$C$61),$C$59/($C$61-$C$60+1),0)+IF(E$5>$C$61,$C$62,0) -> 0 | F102: =IF(AND(F$5>=$C$60,F$5<=$C$61),$C$59/($C$61-$C$60+1),0)+IF(F$5>$C$61,$C$62,0) -> 30 | G102: =IF(AND(G$5>=$C$60,G$5<=$C$61),$C$59/($C$61-$C$60+1),0)+IF(G$5>$C$61,$C$62,0) -> 30 | H102: =IF(AND(H$5>=$C$60,H$5<=$C$61),$C$59/($C$61-$C$60+1),0)+IF(H$5>$C$61,$C$62,0) -> 4 | I102: =IF(AND(I$5>=$C$60,I$5<=$C$61),$C$59/($C$61-$C$60+1),0)+IF(I$5>$C$61,$C$62,0) -> 4 | J102: =IF(AND(J$5>=$C$60,J$5<=$C$61),$C$59/($C$61-$C$60+1),0)+IF(J$5>$C$61,$C$62,0) -> 4 | K102: =IF(AND(K$5>=$C$60,K$5<=$C$61),$C$59/($C$61-$C$60+1),0)+IF(K$5>$C$61,$C$62,0) -> 4 | ... O102: =IF(AND(O$5>=$C$60,O$5<=$C$61),$C$59/($C$61-$C$60+1),0)+IF(O$5>$C$61,$C$62,0) -> 4 | Q102: =SUMIF($D$6:$O$6,Q$6,$D102:$O102) -> 60 | R102: =SUMIF($D$6:$O$6,R$6,$D102:$O102) -> 16 | S102: =SUMIF($D$6:$O$6,S$6,$D102:$O102) -> 16 | T102: =SUM(Q102:S102) -> 92
A103: Затраты до резерва | B103: млн ₽ | D103: =D96+D98+D99+D100+D101+D102 -> 20.25 | E103: =E96+E98+E99+E100+E101+E102 -> 22.75 | F103: =F96+F98+F99+F100+F101+F102 -> 53.036111 | G103: =G96+G98+G99+G100+G101+G102 -> 53.322222 | H103: =H96+H98+H99+H100+H101+H102 -> 35.773702 | I103: =I96+I98+I99+I100+I101+I102 -> 36.559553 | J103: =J96+J98+J99+J100+J101+J102 -> 37.345404 | K103: =K96+K98+K99+K100+K101+K102 -> 38.131255 | ... O103: =O96+O98+O99+O100+O101+O102 -> 47.098849 | Q103: =SUMIF($D$6:$O$6,Q$6,$D103:$O103) -> 149.35833 | R103: =SUMIF($D$6:$O$6,R$6,$D103:$O103) -> 147.80991 | S103: =SUMIF($D$6:$O$6,S$6,$D103:$O103) -> 182.3247 | T103: =SUM(Q103:S103) -> 479.49294
A104: Резерв | B104: млн ₽ | D104: =D103*$C$58 -> 2.025 | E104: =E103*$C$58 -> 2.275 | F104: =F103*$C$58 -> 5.3036111 | G104: =G103*$C$58 -> 5.3322222 | H104: =H103*$C$58 -> 3.5773702 | I104: =I103*$C$58 -> 3.6559553 | J104: =J103*$C$58 -> 3.7345404 | K104: =K103*$C$58 -> 3.8131255 | ... O104: =O103*$C$58 -> 4.7098849 | Q104: =SUMIF($D$6:$O$6,Q$6,$D104:$O104) -> 14.935833 | R104: =SUMIF($D$6:$O$6,R$6,$D104:$O104) -> 14.780991 | S104: =SUMIF($D$6:$O$6,S$6,$D104:$O104) -> 18.23247 | T104: =SUM(Q104:S104) -> 47.949294
A105: Затраты всего | B105: млн ₽ | D105: =D103+D104 -> 22.275 | E105: =E103+E104 -> 25.025 | F105: =F103+F104 -> 58.339722 | G105: =G103+G104 -> 58.654444 | H105: =H103+H104 -> 39.351072 | I105: =I103+I104 -> 40.215509 | J105: =J103+J104 -> 41.079945 | K105: =K103+K104 -> 41.944381 | ... O105: =O103+O104 -> 51.808734 | Q105: =SUMIF($D$6:$O$6,Q$6,$D105:$O105) -> 164.29417 | R105: =SUMIF($D$6:$O$6,R$6,$D105:$O105) -> 162.59091 | S105: =SUMIF($D$6:$O$6,S$6,$D105:$O105) -> 200.55717 | T105: =SUM(Q105:S105) -> 527.44224
...

Sheet Модель_База
A1: Финмодель - сценарий: База
A2: Номер сценария на листе (1 = Пессимист, 2 = База, 3 = Оптимист) | C2: 2
A3: Сценарий | C3: =INDEX(Допущения!$C$4:$E$4,$C$2) -> База
A4: Деньги — млн ₽, объёмы — тыс. шт. за квартал. Допущения — с листа «Допущения».
A5: Квартал № | D5: 1 | E5: =D5+1 -> 2 | F5: =E5+1 -> 3 | G5: =F5+1 -> 4 | H5: =G5+1 -> 5 | I5: =H5+1 -> 6 | J5: =I5+1 -> 7 | K5: =J5+1 -> 8 | L5: =K5+1 -> 9 | ... O5: =N5+1 -> 12
A6: Год проекта | D6: =ROUNDUP(D5/4,0) -> 1 | E6: =ROUNDUP(E5/4,0) -> 1 | F6: =ROUNDUP(F5/4,0) -> 1 | G6: =ROUNDUP(G5/4,0) -> 1 | H6: =ROUNDUP(H5/4,0) -> 2 | I6: =ROUNDUP(I5/4,0) -> 2 | J6: =ROUNDUP(J5/4,0) -> 2 | K6: =ROUNDUP(K5/4,0) -> 2 | ... O6: =ROUNDUP(O5/4,0) -> 3 | Q6: 1 | R6: 2 | S6: 3
A7: Период | C7: Параметр | D7: ="Q"&(MOD(D5-1,4)+1)&" "&(2026+D6) -> Q1 2027 | E7: ="Q"&(MOD(E5-1,4)+1)&" "&(2026+E6) -> Q2 2027 | F7: ="Q"&(MOD(F5-1,4)+1)&" "&(2026+F6) -> Q3 2027 | G7: ="Q"&(MOD(G5-1,4)+1)&" "&(2026+G6) -> Q4 2027 | H7: ="Q"&(MOD(H5-1,4)+1)&" "&(2026+H6) -> Q1 2028 | I7: ="Q"&(MOD(I5-1,4)+1)&" "&(2026+I6) -> Q2 2028 | J7: ="Q"&(MOD(J5-1,4)+1)&" "&(2026+J6) -> Q3 2028 | K7: ="Q"&(MOD(K5-1,4)+1)&" "&(2026+K6) -> Q4 2028 | ... O7: ="Q"&(MOD(O5-1,4)+1)&" "&(2026+O6) -> Q4 2029 | Q7: 2027 | R7: 2028 | S7: 2029 | T7: Итого
A9: Параметры сценария (из листа «Допущения»)
A10: Лимит инвестиций (потолок, не цель) | B10: млн ₽ | C10: =INDEX(Допущения!$C$6:$E$6,$C$2) -> 10000
A11: Максимальный срок окупаемости | B11: кварталов | C11: =INDEX(Допущения!$C$7:$E$7,$C$2) -> 12
A12: Ставка дисконтирования (годовая) | B12: % год | C12: =INDEX(Допущения!$C$8:$E$8,$C$2) -> 0.15
A13: Маржа инкрементального дохода (после переменных издержек сделок) | B13: % | C13: =INDEX(Допущения!$C$9:$E$9,$C$2) -> 0.85
A14: Товарные сделки на платформе в год (база 2026) | B14: млн шт. | C14: =INDEX(Допущения!$C$11:$E$11,$C$2) -> 200
A15: Рост числа товарных сделок в год | B15: % год | C15: =INDEX(Допущения!$C$12:$E$12,$C$2) -> 0.07
A16: Доля товарных сделок с Авито Доставкой (2026) | B16: % | C16: =INDEX(Допущения!$C$13:$E$13,$C$2) -> 0.4
A17: Рост доли Доставки в год | B17: п.п./год | C17: =INDEX(Допущения!$C$14:$E$14,$C$2) -> 0.03
A18: Месячная аудитория Авито | B18: млн чел. | C18: =INDEX(Допущения!$C$15:$E$15,$C$2) -> 51
A19: Доля сделок Доставки в охваченных категориях — Год 1 | B19: % | C19: =INDEX(Допущения!$C$17:$E$17,$C$2) -> 0.31
A20: то же — Год 2 | B20: % | C20: =INDEX(Допущения!$C$18:$E$18,$C$2) -> 0.55
A21: то же — Год 3 | B21: % | C21: =INDEX(Допущения!$C$19:$E$19,$C$2) -> 0.7
A22: Доля сделок, идущих через карточки с блоком опыта (на зрелости) | B22: % | C22: =INDEX(Допущения!$C$20:$E$20,$C$2) -> 0.45
A23: Доля подтверждённых покупателей, оставивших отзыв о модели (на зрелости) | B23: % | C23: =INDEX(Допущения!$C$22:$E$22,$C$2) -> 0.08
A24: Доля авторов, обновивших отзыв позже / с долгим сроком использования | B24: % | C24: =INDEX(Допущения!$C$23:$E$23,$C$2) -> 0.25
A25: Срок использования до пуша «оцените и продайте» | B25: кварталов | C25: =INDEX(Допущения!$C$24:$E$24,$C$2) -> 2
A26: Доля обновивших отзыв, выставивших вещь через «Можно продать» | B26: % | C26: =INDEX(Допущения!$C$25:$E$25,$C$2) -> 0.08
A27: Доля выставивших вещь, купивших продвижение | B27: % | C27: =INDEX(Допущения!$C$26:$E$26,$C$2) -> 0.18
A28: Средний платёж за продвижение | B28: ₽ | C28: =INDEX(Допущения!$C$27:$E$27,$C$2) -> 200
A29: Доля выставленных вещей, проданных через Доставку | B29: % | C29: =INDEX(Допущения!$C$28:$E$28,$C$2) -> 0.3
A30: Прирост конверсии в сделку в карточках с блоком (относительный) | B30: % | C30: =INDEX(Допущения!$C$30:$E$30,$C$2) -> 0.05
A31: Негативный эффект: потеря сделок в охваченных карточках (слабые модели, меньше контактов) | B31: % | C31: =INDEX(Допущения!$C$32:$E$32,$C$2) -> 0.003
A32: Доля прироста, действительно инкрементальная | B32: % | C32: =INDEX(Допущения!$C$31:$E$31,$C$2) -> 0.75
A33: Средний чек сделки с Доставкой | B33: ₽ | C33: =INDEX(Допущения!$C$33:$E$33,$C$2) -> 2000
A34: Доход Авито с оборота сделки через Доставку | B34: % | C34: =INDEX(Допущения!$C$34:$E$34,$C$2) -> 0.125
A35: Индексация среднего чека и комиссии в год (сложный процент) | B35: % год | C35: =INDEX(Допущения!$C$35:$E$35,$C$2) -> 0.06
A36: Доход Авито с одной сделки через Доставку | B36: ₽ | C36: =$C$33*$C$34 -> 250
A37: Доля аудитории охваченных категорий, пользующаяся блоком в месяц (на зрелости) | B37: % | C37: =INDEX(Допущения!$C$37:$E$37,$C$2) -> 0.15
A38: Дополнительных визитов на участника в месяц | B38: визитов | C38: =INDEX(Допущения!$C$38:$E$38,$C$2) -> 0.8
A39: Просмотров за дополнительный визит | B39: шт. | C39: =INDEX(Допущения!$C$39:$E$39,$C$2) -> 10
A40: Доход от рекламы и рекомендаций на один просмотр | B40: ₽ | C40: =INDEX(Допущения!$C$40:$E$40,$C$2) -> 0.08
A41: Доп. сделок в год на участника за счёт удержания (по всей платформе) | B41: сделок/год | C41: =INDEX(Допущения!$C$42:$E$42,$C$2) -> 0
A42: Средний доход Авито со сделки на платформе | B42: ₽ | C42: =INDEX(Допущения!$C$43:$E$43,$C$2) -> 200
A43: Численность команды, Год 1 | B43: FTE | C43: =Допущения!C54*INDEX(Допущения!$C$57:$E$57,$C$2) -> 12.75
A44: Численность команды, Год 2 | B44: FTE | C44: =Допущения!D54*INDEX(Допущения!$C$57:$E$57,$C$2) -> 16.15
A45: Численность команды, Год 3 | B45: FTE | C45: =Допущения!E54*INDEX(Допущения!$C$57:$E$57,$C$2) -> 17
A46: Стоимость 1 FTE в месяц (с налогами и накладными) | B46: тыс. ₽ | C46: =INDEX(Допущения!$C$58:$E$58,$C$2) -> 450
A47: Индексация ФОТ в год | B47: % год | C47: =INDEX(Допущения!$C$59:$E$59,$C$2) -> 0.08
A48: Сообщений в обсуждениях на один отзыв | B48: шт. | C48: =INDEX(Допущения!$C$61:$E$61,$C$2) -> 2
A49: Стоимость ИИ-модерации одного объекта | B49: ₽ | C49: =INDEX(Допущения!$C$62:$E$62,$C$2) -> 1
A50: Доля спорных объектов (ручная проверка) | B50: % | C50: =INDEX(Допущения!$C$63:$E$63,$C$2) -> 0.04
A51: Стоимость ручной проверки | B51: ₽ | C51: =INDEX(Допущения!$C$64:$E$64,$C$2) -> 20
A52: ИИ: генерация пересказов и ИИ-ответов, на 1 отзыв | B52: ₽ | C52: =INDEX(Допущения!$C$65:$E$65,$C$2) -> 2
A53: Инфраструктура и хранение (фикс.) в квартал | B53: млн ₽ | C53: =INDEX(Допущения!$C$66:$E$66,$C$2) -> 2.5
A54: Первый квартал инфраструктурных затрат | B54: № кв. | C54: =INDEX(Допущения!$C$67:$E$67,$C$2) -> 2
A55: Доля отзывов, получающих бонус/пожертвование | B55: % | C55: =INDEX(Допущения!$C$68:$E$68,$C$2) -> 0.5
A56: Сумма бонуса/пожертвования за отзыв | B56: ₽ | C56: =INDEX(Допущения!$C$69:$E$69,$C$2) -> 25
A57: Годовой потолок бюджета на мотивацию | B57: млн ₽/год | C57: =INDEX(Допущения!$C$70:$E$70,$C$2) -> 150
A58: Резерв на непредвиденные затраты | B58: % | C58: =INDEX(Допущения!$C$71:$E$71,$C$2) -> 0.1
A59: Разовый маркетинг запуска | B59: млн ₽ | C59: =INDEX(Допущения!$C$73:$E$73,$C$2) -> 50
A60: Первый квартал маркетинга запуска | B60: № кв. | C60: =INDEX(Допущения!$C$74:$E$74,$C$2) -> 3
A61: Последний квартал маркетинга запуска | B61: № кв. | C61: =INDEX(Допущения!$C$75:$E$75,$C$2) -> 4
A62: Текущий маркетинг и тесты после запуска, в квартал | B62: млн ₽ | C62: =INDEX(Допущения!$C$76:$E$76,$C$2) -> 4
A64: A. Объёмы и охват
A65: Товарные сделки на платформе | B65: тыс. шт. | D65: =$C$14*1000*(1+$C$15)^D$6/4 -> 53500 | E65: =$C$14*1000*(1+$C$15)^E$6/4 -> 53500 | F65: =$C$14*1000*(1+$C$15)^F$6/4 -> 53500 | G65: =$C$14*1000*(1+$C$15)^G$6/4 -> 53500 | H65: =$C$14*1000*(1+$C$15)^H$6/4 -> 57245 | I65: =$C$14*1000*(1+$C$15)^I$6/4 -> 57245 | J65: =$C$14*1000*(1+$C$15)^J$6/4 -> 57245 | K65: =$C$14*1000*(1+$C$15)^K$6/4 -> 57245 | ... O65: =$C$14*1000*(1+$C$15)^O$6/4 -> 61252.15 | Q65: =SUMIF($D$6:$O$6,Q$6,$D65:$O65) -> 214000 | R65: =SUMIF($D$6:$O$6,R$6,$D65:$O65) -> 228980 | S65: =SUMIF($D$6:$O$6,S$6,$D65:$O65) -> 245008.6 | T65: =SUM(Q65:S65) -> 687988.6
A66: Доля сделок через Доставку | B66: % | D66: =$C$16+$C$17*D$6 -> 0.43 | E66: =$C$16+$C$17*E$6 -> 0.43 | F66: =$C$16+$C$17*F$6 -> 0.43 | G66: =$C$16+$C$17*G$6 -> 0.43 | H66: =$C$16+$C$17*H$6 -> 0.46 | I66: =$C$16+$C$17*I$6 -> 0.46 | J66: =$C$16+$C$17*J$6 -> 0.46 | K66: =$C$16+$C$17*K$6 -> 0.46 | ... O66: =$C$16+$C$17*O$6 -> 0.49
A67: Сделки через Доставку | B67: тыс. шт. | D67: =D65*D66 -> 23005 | E67: =E65*E66 -> 23005 | F67: =F65*F66 -> 23005 | G67: =G65*G66 -> 23005 | H67: =H65*H66 -> 26332.7 | I67: =I65*I66 -> 26332.7 | J67: =J65*J66 -> 26332.7 | K67: =K65*K66 -> 26332.7 | ... O67: =O65*O66 -> 30013.554 | Q67: =SUMIF($D$6:$O$6,Q$6,$D67:$O67) -> 92020 | R67: =SUMIF($D$6:$O$6,R$6,$D67:$O67) -> 105330.8 | S67: =SUMIF($D$6:$O$6,S$6,$D67:$O67) -> 120054.21 | T67: =SUM(Q67:S67) -> 317405.01
A68: Охват категорий механикой (доля сделок Доставки) | B68: % | D68: =INDEX($C$19:$C$21,D$6) -> 0.31 | E68: =INDEX($C$19:$C$21,E$6) -> 0.31 | F68: =INDEX($C$19:$C$21,F$6) -> 0.31 | G68: =INDEX($C$19:$C$21,G$6) -> 0.31 | H68: =INDEX($C$19:$C$21,H$6) -> 0.55 | I68: =INDEX($C$19:$C$21,I$6) -> 0.55 | J68: =INDEX($C$19:$C$21,J$6) -> 0.55 | K68: =INDEX($C$19:$C$21,K$6) -> 0.55 | ... O68: =INDEX($C$19:$C$21,O$6) -> 0.7
A69: Профиль зрелости запуска | B69: % | D69: =INDEX(Допущения!D$79:D$81,$C$2) -> 0 | E69: =INDEX(Допущения!E$79:E$81,$C$2) -> 0 | F69: =INDEX(Допущения!F$79:F$81,$C$2) -> 0.12 | G69: =INDEX(Допущения!G$79:G$81,$C$2) -> 0.3 | H69: =INDEX(Допущения!H$79:H$81,$C$2) -> 0.48 | I69: =INDEX(Допущения!I$79:I$81,$C$2) -> 0.65 | J69: =INDEX(Допущения!J$79:J$81,$C$2) -> 0.8 | K69: =INDEX(Допущения!K$79:K$81,$C$2) -> 0.92 | ... O69: =INDEX(Допущения!O$79:O$81,$C$2) -> 1
A70: Сделки Доставки в охваченных категориях | B70: тыс. шт. | D70: =D67*D68 -> 7131.55 | E70: =E67*E68 -> 7131.55 | F70: =F67*F68 -> 7131.55 | G70: =G67*G68 -> 7131.55 | H70: =H67*H68 -> 14482.985 | I70: =I67*I68 -> 14482.985 | J70: =J67*J68 -> 14482.985 | K70: =K67*K68 -> 14482.985 | ... O70: =O67*O68 -> 21009.487 | Q70: =SUMIF($D$6:$O$6,Q$6,$D70:$O70) -> 28526.2 | R70: =SUMIF($D$6:$O$6,R$6,$D70:$O70) -> 57931.94 | S70: =SUMIF($D$6:$O$6,S$6,$D70:$O70) -> 84037.95 | T70: =SUM(Q70:S70) -> 170496.09
A71: из них — в карточках с блоком опыта | B71: тыс. шт. | D71: =D70*$C$22*D69 -> 0 | E71: =E70*$C$22*E69 -> 0 | F71: =F70*$C$22*F69 -> 385.1037 | G71: =G70*$C$22*G69 -> 962.75925 | H71: =H70*$C$22*H69 -> 3128.3248 | I71: =I70*$C$22*I69 -> 4236.2731 | J71: =J70*$C$22*J69 -> 5213.8746 | K71: =K70*$C$22*K69 -> 5995.9558 | ... O71: =O70*$C$22*O69 -> 9454.2694 | Q71: =SUMIF($D$6:$O$6,Q$6,$D71:$O71) -> 1347.8629 | R71: =SUMIF($D$6:$O$6,R$6,$D71:$O71) -> 18574.428 | S71: =SUMIF($D$6:$O$6,S$6,$D71:$O71) -> 37817.077 | T71: =SUM(Q71:S71) -> 57739.369
A73: B. Воронка отзывов
A74: Отзывы о моделях (подтверждённые покупатели) | B74: тыс. шт. | D74: =D70*D69*$C$23 -> 0 | E74: =E70*E69*$C$23 -> 0 | F74: =F70*F69*$C$23 -> 68.46288 | G74: =G70*G69*$C$23 -> 171.1572 | H74: =H70*H69*$C$23 -> 556.14662 | I74: =I70*I69*$C$23 -> 753.11522 | J74: =J70*J69*$C$23 -> 926.91104 | K74: =K70*K69*$C$23 -> 1065.9477 | ... O74: =O70*O69*$C$23 -> 1680.759 | Q74: =SUMIF($D$6:$O$6,Q$6,$D74:$O74) -> 239.62008 | R74: =SUMIF($D$6:$O$6,R$6,$D74:$O74) -> 3302.1206 | S74: =SUMIF($D$6:$O$6,S$6,$D74:$O74) -> 6723.036 | T74: =SUM(Q74:S74) -> 10264.777
A75: Авторы с долгим сроком использования / обновили отзыв | B75: тыс. шт. | D75: =IF(D$5>$C$25,INDEX($D$74:$O$74,D$5-$C$25),0)*$C$24 -> 0 | E75: =IF(E$5>$C$25,INDEX($D$74:$O$74,E$5-$C$25),0)*$C$24 -> 0 | F75: =IF(F$5>$C$25,INDEX($D$74:$O$74,F$5-$C$25),0)*$C$24 -> 0 | G75: =IF(G$5>$C$25,INDEX($D$74:$O$74,G$5-$C$25),0)*$C$24 -> 0 | H75: =IF(H$5>$C$25,INDEX($D$74:$O$74,H$5-$C$25),0)*$C$24 -> 17.11572 | I75: =IF(I$5>$C$25,INDEX($D$74:$O$74,I$5-$C$25),0)*$C$24 -> 42.7893 | J75: =IF(J$5>$C$25,INDEX($D$74:$O$74,J$5-$C$25),0)*$C$24 -> 139.03666 | K75: =IF(K$5>$C$25,INDEX($D$74:$O$74,K$5-$C$25),0)*$C$24 -> 188.27881 | ... O75: =IF(O$5>$C$25,INDEX($D$74:$O$74,O$5-$C$25),0)*$C$24 -> 420.18975 | Q75: =SUMIF($D$6:$O$6,Q$6,$D75:$O75) -> 0 | R75: =SUMIF($D$6:$O$6,R$6,$D75:$O75) -> 387.22048 | S75: =SUMIF($D$6:$O$6,S$6,$D75:$O75) -> 1338.5942 | T75: =SUM(Q75:S75) -> 1725.8147
A76: Выставили вещь через «Можно продать» | B76: тыс. шт. | D76: =D75*$C$26 -> 0 | E76: =E75*$C$26 -> 0 | F76: =F75*$C$26 -> 0 | G76: =G75*$C$26 -> 0 | H76: =H75*$C$26 -> 1.3692576 | I76: =I75*$C$26 -> 3.423144 | J76: =J75*$C$26 -> 11.122932 | K76: =K75*$C$26 -> 15.062304 | ... O76: =O75*$C$26 -> 33.61518 | Q76: =SUMIF($D$6:$O$6,Q$6,$D76:$O76) -> 0 | R76: =SUMIF($D$6:$O$6,R$6,$D76:$O76) -> 30.977638 | S76: =SUMIF($D$6:$O$6,S$6,$D76:$O76) -> 107.08753 | T76: =SUM(Q76:S76) -> 138.06517
A77: Купили продвижение | B77: тыс. шт. | D77: =D76*$C$27 -> 0 | E77: =E76*$C$27 -> 0 | F77: =F76*$C$27 -> 0 | G77: =G76*$C$27 -> 0 | H77: =H76*$C$27 -> 0.24646637 | I77: =I76*$C$27 -> 0.61616592 | J77: =J76*$C$27 -> 2.0021278 | K77: =K76*$C$27 -> 2.7112148 | ... O77: =O76*$C$27 -> 6.0507324 | Q77: =SUMIF($D$6:$O$6,Q$6,$D77:$O77) -> 0 | R77: =SUMIF($D$6:$O$6,R$6,$D77:$O77) -> 5.5759749 | S77: =SUMIF($D$6:$O$6,S$6,$D77:$O77) -> 19.275756 | T77: =SUM(Q77:S77) -> 24.851731
A79: C. Эффекты (дополнительная выручка Авито)
A80: Доход Авито с одной сделки через Доставку (с индексацией) | B80: ₽ | D80: =$C$36*(1+$C$35)^(D$6-1) -> 250 | E80: =$C$36*(1+$C$35)^(E$6-1) -> 250 | F80: =$C$36*(1+$C$35)^(F$6-1) -> 250 | G80: =$C$36*(1+$C$35)^(G$6-1) -> 250 | H80: =$C$36*(1+$C$35)^(H$6-1) -> 265 | I80: =$C$36*(1+$C$35)^(I$6-1) -> 265 | J80: =$C$36*(1+$C$35)^(J$6-1) -> 265 | K80: =$C$36*(1+$C$35)^(K$6-1) -> 265 | ... O80: =$C$36*(1+$C$35)^(O$6-1) -> 280.9 | Q80: =AVERAGEIF($D$6:$O$6,Q$6,$D80:$O80) -> 250 | R80: =AVERAGEIF($D$6:$O$6,R$6,$D80:$O80) -> 265 | S80: =AVERAGEIF($D$6:$O$6,S$6,$D80:$O80) -> 280.9
A81: Эффект 1: прирост сделок (инкрементальный) | B81: тыс. шт. | D81: =D71*$C$30*$C$32 -> 0 | E81: =E71*$C$30*$C$32 -> 0 | F81: =F71*$C$30*$C$32 -> 14.441389 | G81: =G71*$C$30*$C$32 -> 36.103472 | H81: =H71*$C$30*$C$32 -> 117.31218 | I81: =I71*$C$30*$C$32 -> 158.86024 | J81: =J71*$C$30*$C$32 -> 195.5203 | K81: =K71*$C$30*$C$32 -> 224.84834 | ... O81: =O71*$C$30*$C$32 -> 354.5351 | Q81: =SUMIF($D$6:$O$6,Q$6,$D81:$O81) -> 50.544861 | R81: =SUMIF($D$6:$O$6,R$6,$D81:$O81) -> 696.54106 | S81: =SUMIF($D$6:$O$6,S$6,$D81:$O81) -> 1418.1404 | T81: =SUM(Q81:S81) -> 2165.2263
A82: Эффект 1: потеря сделок (слабые модели, меньше контактов) | B82: тыс. шт. | D82: =D71*$C$31 -> 0 | E82: =E71*$C$31 -> 0 | F82: =F71*$C$31 -> 1.1553111 | G82: =G71*$C$31 -> 2.8882777 | H82: =H71*$C$31 -> 9.3849743 | I82: =I71*$C$31 -> 12.708819 | J82: =J71*$C$31 -> 15.641624 | K82: =K71*$C$31 -> 17.987867 | ... O82: =O71*$C$31 -> 28.362808 | Q82: =SUMIF($D$6:$O$6,Q$6,$D82:$O82) -> 4.0435888 | R82: =SUMIF($D$6:$O$6,R$6,$D82:$O82) -> 55.723285 | S82: =SUMIF($D$6:$O$6,S$6,$D82:$O82) -> 113.45123 | T82: =SUM(Q82:S82) -> 173.21811
A83: Эффект 1: чистый прирост сделок | B83: тыс. шт. | D83: =D81-D82 -> 0 | E83: =E81-E82 -> 0 | F83: =F81-F82 -> 13.286078 | G83: =G81-G82 -> 33.215194 | H83: =H81-H82 -> 107.9272 | I83: =I81-I82 -> 146.15142 | J83: =J81-J82 -> 179.87867 | K83: =K81-K82 -> 206.86047 | ... O83: =O81-O82 -> 326.17229 | Q83: =SUMIF($D$6:$O$6,Q$6,$D83:$O83) -> 46.501272 | R83: =SUMIF($D$6:$O$6,R$6,$D83:$O83) -> 640.81778 | S83: =SUMIF($D$6:$O$6,S$6,$D83:$O83) -> 1304.6892 | T83: =SUM(Q83:S83) -> 1992.0082
A84: Эффект 1: доход от конверсии (комиссия Доставки) | B84: млн ₽ | D84: =D83*D80/1000 -> 0 | E84: =E83*E80/1000 -> 0 | F84: =F83*F80/1000 -> 3.3215194 | G84: =G83*G80/1000 -> 8.3037985 | H84: =H83*H80/1000 -> 28.600709 | I84: =I83*I80/1000 -> 38.730127 | J84: =J83*J80/1000 -> 47.667849 | K84: =K83*K80/1000 -> 54.818026 | ... O84: =O83*O80/1000 -> 91.621797 | Q84: =SUMIF($D$6:$O$6,Q$6,$D84:$O84) -> 11.625318 | R84: =SUMIF($D$6:$O$6,R$6,$D84:$O84) -> 169.81671 | S84: =SUMIF($D$6:$O$6,S$6,$D84:$O84) -> 366.48719 | T84: =SUM(Q84:S84) -> 547.92922
A85: Эффект 2: доход от продвижения новых объявлений | B85: млн ₽ | D85: =D77*$C$28/1000 -> 0 | E85: =E77*$C$28/1000 -> 0 | F85: =F77*$C$28/1000 -> 0 | G85: =G77*$C$28/1000 -> 0 | H85: =H77*$C$28/1000 -> 0.049293274 | I85: =I77*$C$28/1000 -> 0.12323318 | J85: =J77*$C$28/1000 -> 0.40042557 | K85: =K77*$C$28/1000 -> 0.54224296 | ... O85: =O77*$C$28/1000 -> 1.2101465 | Q85: =SUMIF($D$6:$O$6,Q$6,$D85:$O85) -> 0 | R85: =SUMIF($D$6:$O$6,R$6,$D85:$O85) -> 1.115195 | S85: =SUMIF($D$6:$O$6,S$6,$D85:$O85) -> 3.8551512 | T85: =SUM(Q85:S85) -> 4.9703462
A86: Эффект 2: доход со сделок по новым объявлениям | B86: млн ₽ | D86: =D76*$C$29*D80/1000 -> 0 | E86: =E76*$C$29*E80/1000 -> 0 | F86: =F76*$C$29*F80/1000 -> 0 | G86: =G76*$C$29*G80/1000 -> 0 | H86: =H76*$C$29*H80/1000 -> 0.10885598 | I86: =I76*$C$29*I80/1000 -> 0.27213995 | J86: =J76*$C$29*J80/1000 -> 0.88427313 | K86: =K76*$C$29*K80/1000 -> 1.1974532 | ... O86: =O76*$C$29*O80/1000 -> 2.8327512 | Q86: =SUMIF($D$6:$O$6,Q$6,$D86:$O86) -> 0 | R86: =SUMIF($D$6:$O$6,R$6,$D86:$O86) -> 2.4627223 | S86: =SUMIF($D$6:$O$6,S$6,$D86:$O86) -> 9.0242665 | T86: =SUM(Q86:S86) -> 11.486989
A87: Участники блока в месяц (аудитория) | B87: тыс. чел. | D87: =$C$18*1000*D68*$C$37*D69 -> 0 | E87: =$C$18*1000*E68*$C$37*E69 -> 0 | F87: =$C$18*1000*F68*$C$37*F69 -> 284.58 | G87: =$C$18*1000*G68*$C$37*G69 -> 711.45 | H87: =$C$18*1000*H68*$C$37*H69 -> 2019.6 | I87: =$C$18*1000*I68*$C$37*I69 -> 2734.875 | J87: =$C$18*1000*J68*$C$37*J69 -> 3366 | K87: =$C$18*1000*K68*$C$37*K69 -> 3870.9 | ... O87: =$C$18*1000*O68*$C$37*O69 -> 5355 | Q87: =AVERAGEIF($D$6:$O$6,Q$6,$D87:$O87) -> 249.0075 | R87: =AVERAGEIF($D$6:$O$6,R$6,$D87:$O87) -> 2997.8438 | S87: =AVERAGEIF($D$6:$O$6,S$6,$D87:$O87) -> 5355
A88: Эффект 3: дополнительные просмотры за квартал | B88: тыс. шт. | D88: =D87*$C$38*3*$C$39 -> 0 | E88: =E87*$C$38*3*$C$39 -> 0 | F88: =F87*$C$38*3*$C$39 -> 6829.92 | G88: =G87*$C$38*3*$C$39 -> 17074.8 | H88: =H87*$C$38*3*$C$39 -> 48470.4 | I88: =I87*$C$38*3*$C$39 -> 65637 | J88: =J87*$C$38*3*$C$39 -> 80784 | K88: =K87*$C$38*3*$C$39 -> 92901.6 | ... O88: =O87*$C$38*3*$C$39 -> 128520 | Q88: =SUMIF($D$6:$O$6,Q$6,$D88:$O88) -> 23904.72 | R88: =SUMIF($D$6:$O$6,R$6,$D88:$O88) -> 287793 | S88: =SUMIF($D$6:$O$6,S$6,$D88:$O88) -> 514080 | T88: =SUM(Q88:S88) -> 825777.72
A89: Эффект 3: доход от рекламы и рекомендаций | B89: млн ₽ | D89: =D88*$C$40/1000 -> 0 | E89: =E88*$C$40/1000 -> 0 | F89: =F88*$C$40/1000 -> 0.5463936 | G89: =G88*$C$40/1000 -> 1.365984 | H89: =H88*$C$40/1000 -> 3.877632 | I89: =I88*$C$40/1000 -> 5.25096 | J89: =J88*$C$40/1000 -> 6.46272 | K89: =K88*$C$40/1000 -> 7.432128 | ... O89: =O88*$C$40/1000 -> 10.2816 | Q89: =SUMIF($D$6:$O$6,Q$6,$D89:$O89) -> 1.9123776 | R89: =SUMIF($D$6:$O$6,R$6,$D89:$O89) -> 23.02344 | S89: =SUMIF($D$6:$O$6,S$6,$D89:$O89) -> 41.1264 | T89: =SUM(Q89:S89) -> 66.062218
A90: Эффект 4: удержание (верхний сценарий) | B90: млн ₽ | D90: =D87*$C$41/4*$C$42/1000 -> 0 | E90: =E87*$C$41/4*$C$42/1000 -> 0 | F90: =F87*$C$41/4*$C$42/1000 -> 0 | G90: =G87*$C$41/4*$C$42/1000 -> 0 | H90: =H87*$C$41/4*$C$42/1000 -> 0 | I90: =I87*$C$41/4*$C$42/1000 -> 0 | J90: =J87*$C$41/4*$C$42/1000 -> 0 | K90: =K87*$C$41/4*$C$42/1000 -> 0 | ... O90: =O87*$C$41/4*$C$42/1000 -> 0 | Q90: =SUMIF($D$6:$O$6,Q$6,$D90:$O90) -> 0 | R90: =SUMIF($D$6:$O$6,R$6,$D90:$O90) -> 0 | S90: =SUMIF($D$6:$O$6,S$6,$D90:$O90) -> 0 | T90: =SUM(Q90:S90) -> 0
A91: Дополнительная выручка всего | B91: млн ₽ | D91: =D84+D85+D86+D89+D90 -> 0 | E91: =E84+E85+E86+E89+E90 -> 0 | F91: =F84+F85+F86+F89+F90 -> 3.867913 | G91: =G84+G85+G86+G89+G90 -> 9.6697825 | H91: =H84+H85+H86+H89+H90 -> 32.63649 | I91: =I84+I85+I86+I89+I90 -> 44.37646 | J91: =J84+J85+J86+J89+J90 -> 55.415267 | K91: =K84+K85+K86+K89+K90 -> 63.98985 | ... O91: =O84+O85+O86+O89+O90 -> 105.94629 | Q91: =SUMIF($D$6:$O$6,Q$6,$D91:$O91) -> 13.537696 | R91: =SUMIF($D$6:$O$6,R$6,$D91:$O91) -> 196.41807 | S91: =SUMIF($D$6:$O$6,S$6,$D91:$O91) -> 420.49301 | T91: =SUM(Q91:S91) -> 630.44877
A92: Маржинальный доход (после переменных издержек) | B92: млн ₽ | D92: =D91*$C$13 -> 0 | E92: =E91*$C$13 -> 0 | F92: =F91*$C$13 -> 3.2877261 | G92: =G91*$C$13 -> 8.2193152 | H92: =H91*$C$13 -> 27.741017 | I92: =I91*$C$13 -> 37.719991 | J92: =J91*$C$13 -> 47.102977 | K92: =K91*$C$13 -> 54.391372 | ... O92: =O91*$C$13 -> 90.05435 | Q92: =SUMIF($D$6:$O$6,Q$6,$D92:$O92) -> 11.507041 | R92: =SUMIF($D$6:$O$6,R$6,$D92:$O92) -> 166.95536 | S92: =SUMIF($D$6:$O$6,S$6,$D92:$O92) -> 357.41905 | T92: =SUM(Q92:S92) -> 535.88145
A94: D. Затраты
A95: Численность команды | B95: FTE | D95: =INDEX($C$43:$C$45,D$6) -> 12.75 | E95: =INDEX($C$43:$C$45,E$6) -> 12.75 | F95: =INDEX($C$43:$C$45,F$6) -> 12.75 | G95: =INDEX($C$43:$C$45,G$6) -> 12.75 | H95: =INDEX($C$43:$C$45,H$6) -> 16.15 | I95: =INDEX($C$43:$C$45,I$6) -> 16.15 | J95: =INDEX($C$43:$C$45,J$6) -> 16.15 | K95: =INDEX($C$43:$C$45,K$6) -> 16.15 | ... O95: =INDEX($C$43:$C$45,O$6) -> 17 | Q95: =AVERAGEIF($D$6:$O$6,Q$6,$D95:$O95) -> 12.75 | R95: =AVERAGEIF($D$6:$O$6,R$6,$D95:$O95) -> 16.15 | S95: =AVERAGEIF($D$6:$O$6,S$6,$D95:$O95) -> 17
A96: Команда разработки | B96: млн ₽ | D96: =D95*$C$46*3*(1+$C$47)^(D$6-1)/1000 -> 17.2125 | E96: =E95*$C$46*3*(1+$C$47)^(E$6-1)/1000 -> 17.2125 | F96: =F95*$C$46*3*(1+$C$47)^(F$6-1)/1000 -> 17.2125 | G96: =G95*$C$46*3*(1+$C$47)^(G$6-1)/1000 -> 17.2125 | H96: =H95*$C$46*3*(1+$C$47)^(H$6-1)/1000 -> 23.5467 | I96: =I95*$C$46*3*(1+$C$47)^(I$6-1)/1000 -> 23.5467 | J96: =J95*$C$46*3*(1+$C$47)^(J$6-1)/1000 -> 23.5467 | K96: =K95*$C$46*3*(1+$C$47)^(K$6-1)/1000 -> 23.5467 | ... O96: =O95*$C$46*3*(1+$C$47)^(O$6-1)/1000 -> 26.76888 | Q96: =SUMIF($D$6:$O$6,Q$6,$D96:$O96) -> 68.85 | R96: =SUMIF($D$6:$O$6,R$6,$D96:$O96) -> 94.1868 | S96: =SUMIF($D$6:$O$6,S$6,$D96:$O96) -> 107.07552 | T96: =SUM(Q96:S96) -> 270.11232
A97: Объекты модерации (отзывы + сообщения) | B97: тыс. шт. | D97: =D74*(1+$C$48) -> 0 | E97: =E74*(1+$C$48) -> 0 | F97: =F74*(1+$C$48) -> 205.38864 | G97: =G74*(1+$C$48) -> 513.4716 | H97: =H74*(1+$C$48) -> 1668.4399 | I97: =I74*(1+$C$48) -> 2259.3457 | J97: =J74*(1+$C$48) -> 2780.7331 | K97: =K74*(1+$C$48) -> 3197.8431 | ... O97: =O74*(1+$C$48) -> 5042.277 | Q97: =SUMIF($D$6:$O$6,Q$6,$D97:$O97) -> 718.86024 | R97: =SUMIF($D$6:$O$6,R$6,$D97:$O97) -> 9906.3617 | S97: =SUMIF($D$6:$O$6,S$6,$D97:$O97) -> 20169.108 | T97: =SUM(Q97:S97) -> 30794.33
A98: ИИ-модерация | B98: млн ₽ | D98: =D97*$C$49/1000 -> 0 | E98: =E97*$C$49/1000 -> 0 | F98: =F97*$C$49/1000 -> 0.20538864 | G98: =G97*$C$49/1000 -> 0.5134716 | H98: =H97*$C$49/1000 -> 1.6684399 | I98: =I97*$C$49/1000 -> 2.2593457 | J98: =J97*$C$49/1000 -> 2.7807331 | K98: =K97*$C$49/1000 -> 3.1978431 | ... O98: =O97*$C$49/1000 -> 5.042277 | Q98: =SUMIF($D$6:$O$6,Q$6,$D98:$O98) -> 0.71886024 | R98: =SUMIF($D$6:$O$6,R$6,$D98:$O98) -> 9.9063617 | S98: =SUMIF($D$6:$O$6,S$6,$D98:$O98) -> 20.169108 | T98: =SUM(Q98:S98) -> 30.79433
A99: Ручная модерация спорных случаев | B99: млн ₽ | D99: =D97*$C$50*$C$51/1000 -> 0 | E99: =E97*$C$50*$C$51/1000 -> 0 | F99: =F97*$C$50*$C$51/1000 -> 0.16431091 | G99: =G97*$C$50*$C$51/1000 -> 0.41077728 | H99: =H97*$C$50*$C$51/1000 -> 1.3347519 | I99: =I97*$C$50*$C$51/1000 -> 1.8074765 | J99: =J97*$C$50*$C$51/1000 -> 2.2245865 | K99: =K97*$C$50*$C$51/1000 -> 2.5582745 | ... O99: =O97*$C$50*$C$51/1000 -> 4.0338216 | Q99: =SUMIF($D$6:$O$6,Q$6,$D99:$O99) -> 0.57508819 | R99: =SUMIF($D$6:$O$6,R$6,$D99:$O99) -> 7.9250894 | S99: =SUMIF($D$6:$O$6,S$6,$D99:$O99) -> 16.135286 | T99: =SUM(Q99:S99) -> 24.635464
A100: ИИ и инфраструктура | B100: млн ₽ | D100: =D74*$C$52/1000+IF(D$5>=$C$54,$C$53,0) -> 0 | E100: =E74*$C$52/1000+IF(E$5>=$C$54,$C$53,0) -> 2.5 | F100: =F74*$C$52/1000+IF(F$5>=$C$54,$C$53,0) -> 2.6369258 | G100: =G74*$C$52/1000+IF(G$5>=$C$54,$C$53,0) -> 2.8423144 | H100: =H74*$C$52/1000+IF(H$5>=$C$54,$C$53,0) -> 3.6122932 | I100: =I74*$C$52/1000+IF(I$5>=$C$54,$C$53,0) -> 4.0062304 | J100: =J74*$C$52/1000+IF(J$5>=$C$54,$C$53,0) -> 4.3538221 | K100: =K74*$C$52/1000+IF(K$5>=$C$54,$C$53,0) -> 4.6318954 | ... O100: =O74*$C$52/1000+IF(O$5>=$C$54,$C$53,0) -> 5.861518 | Q100: =SUMIF($D$6:$O$6,Q$6,$D100:$O100) -> 7.9792402 | R100: =SUMIF($D$6:$O$6,R$6,$D100:$O100) -> 16.604241 | S100: =SUMIF($D$6:$O$6,S$6,$D100:$O100) -> 23.446072 | T100: =SUM(Q100:S100) -> 48.029553
A101: Мотивация авторов (с годовым потолком) | B101: млн ₽ | D101: =MIN(D74*$C$55*$C$56/1000,$C$57/4) -> 0 | E101: =MIN(E74*$C$55*$C$56/1000,$C$57/4) -> 0 | F101: =MIN(F74*$C$55*$C$56/1000,$C$57/4) -> 0.855786 | G101: =MIN(G74*$C$55*$C$56/1000,$C$57/4) -> 2.139465 | H101: =MIN(H74*$C$55*$C$56/1000,$C$57/4) -> 6.9518328 | I101: =MIN(I74*$C$55*$C$56/1000,$C$57/4) -> 9.4139402 | J101: =MIN(J74*$C$55*$C$56/1000,$C$57/4) -> 11.586388 | K101: =MIN(K74*$C$55*$C$56/1000,$C$57/4) -> 13.324346 | ... O101: =MIN(O74*$C$55*$C$56/1000,$C$57/4) -> 21.009487 | Q101: =SUMIF($D$6:$O$6,Q$6,$D101:$O101) -> 2.995251 | R101: =SUMIF($D$6:$O$6,R$6,$D101:$O101) -> 41.276507 | S101: =SUMIF($D$6:$O$6,S$6,$D101:$O101) -> 84.03795 | T101: =SUM(Q101:S101) -> 128.30971
A102: Маркетинг (запуск + текущий) | B102: млн ₽ | D102: =IF(AND(D$5>=$C$60,D$5<=$C$61),$C$59/($C$61-$C$60+1),0)+IF(D$5>$C$61,$C$62,0) -> 0 | E102: =IF(AND(E$5>=$C$60,E$5<=$C$61),$C$59/($C$61-$C$60+1),0)+IF(E$5>$C$61,$C$62,0) -> 0 | F102: =IF(AND(F$5>=$C$60,F$5<=$C$61),$C$59/($C$61-$C$60+1),0)+IF(F$5>$C$61,$C$62,0) -> 25 | G102: =IF(AND(G$5>=$C$60,G$5<=$C$61),$C$59/($C$61-$C$60+1),0)+IF(G$5>$C$61,$C$62,0) -> 25 | H102: =IF(AND(H$5>=$C$60,H$5<=$C$61),$C$59/($C$61-$C$60+1),0)+IF(H$5>$C$61,$C$62,0) -> 4 | I102: =IF(AND(I$5>=$C$60,I$5<=$C$61),$C$59/($C$61-$C$60+1),0)+IF(I$5>$C$61,$C$62,0) -> 4 | J102: =IF(AND(J$5>=$C$60,J$5<=$C$61),$C$59/($C$61-$C$60+1),0)+IF(J$5>$C$61,$C$62,0) -> 4 | K102: =IF(AND(K$5>=$C$60,K$5<=$C$61),$C$59/($C$61-$C$60+1),0)+IF(K$5>$C$61,$C$62,0) -> 4 | ... O102: =IF(AND(O$5>=$C$60,O$5<=$C$61),$C$59/($C$61-$C$60+1),0)+IF(O$5>$C$61,$C$62,0) -> 4 | Q102: =SUMIF($D$6:$O$6,Q$6,$D102:$O102) -> 50 | R102: =SUMIF($D$6:$O$6,R$6,$D102:$O102) -> 16 | S102: =SUMIF($D$6:$O$6,S$6,$D102:$O102) -> 16 | T102: =SUM(Q102:S102) -> 82
A103: Затраты до резерва | B103: млн ₽ | D103: =D96+D98+D99+D100+D101+D102 -> 17.2125 | E103: =E96+E98+E99+E100+E101+E102 -> 19.7125 | F103: =F96+F98+F99+F100+F101+F102 -> 46.074911 | G103: =G96+G98+G99+G100+G101+G102 -> 48.118528 | H103: =H96+H98+H99+H100+H101+H102 -> 41.114018 | I103: =I96+I98+I99+I100+I101+I102 -> 45.033693 | J103: =J96+J98+J99+J100+J101+J102 -> 48.49223 | K103: =K96+K98+K99+K100+K101+K102 -> 51.259059 | ... O103: =O96+O98+O99+O100+O101+O102 -> 66.715984 | Q103: =SUMIF($D$6:$O$6,Q$6,$D103:$O103) -> 131.11844 | R103: =SUMIF($D$6:$O$6,R$6,$D103:$O103) -> 185.899 | S103: =SUMIF($D$6:$O$6,S$6,$D103:$O103) -> 266.86394 | T103: =SUM(Q103:S103) -> 583.88138
A104: Резерв | B104: млн ₽ | D104: =D103*$C$58 -> 1.72125 | E104: =E103*$C$58 -> 1.97125 | F104: =F103*$C$58 -> 4.6074911 | G104: =G103*$C$58 -> 4.8118528 | H104: =H103*$C$58 -> 4.1114018 | I104: =I103*$C$58 -> 4.5033693 | J104: =J103*$C$58 -> 4.849223 | K104: =K103*$C$58 -> 5.1259059 | ... O104: =O103*$C$58 -> 6.6715984 | Q104: =SUMIF($D$6:$O$6,Q$6,$D104:$O104) -> 13.111844 | R104: =SUMIF($D$6:$O$6,R$6,$D104:$O104) -> 18.5899 | S104: =SUMIF($D$6:$O$6,S$6,$D104:$O104) -> 26.686394 | T104: =SUM(Q104:S104) -> 58.388138
A105: Затраты всего | B105: млн ₽ | D105: =D103+D104 -> 18.93375 | E105: =E103+E104 -> 21.68375 | F105: =F103+F104 -> 50.682402 | G105: =G103+G104 -> 52.930381 | H105: =H103+H104 -> 45.22542 | I105: =I103+I104 -> 49.537062 | J105: =J103+J104 -> 53.341453 | K105: =K103+K104 -> 56.384965 | ... O105: =O103+O104 -> 73.387582 | Q105: =SUMIF($D$6:$O$6,Q$6,$D105:$O105) -> 144.23028 | R105: =SUMIF($D$6:$O$6,R$6,$D105:$O105) -> 204.4889 | S105: =SUMIF($D$6:$O$6,S$6,$D105:$O105) -> 293.55033 | T105: =SUM(Q105:S105) -> 642.26951
...

Sheet Модель_Оптимист
A1: Финмодель - сценарий: Оптимист
A2: Номер сценария на листе (1 = Пессимист, 2 = База, 3 = Оптимист) | C2: 3
A3: Сценарий | C3: =INDEX(Допущения!$C$4:$E$4,$C$2) -> Оптимист
A4: Деньги — млн ₽, объёмы — тыс. шт. за квартал. Допущения — с листа «Допущения».
A5: Квартал № | D5: 1 | E5: =D5+1 -> 2 | F5: =E5+1 -> 3 | G5: =F5+1 -> 4 | H5: =G5+1 -> 5 | I5: =H5+1 -> 6 | J5: =I5+1 -> 7 | K5: =J5+1 -> 8 | L5: =K5+1 -> 9 | ... O5: =N5+1 -> 12
A6: Год проекта | D6: =ROUNDUP(D5/4,0) -> 1 | E6: =ROUNDUP(E5/4,0) -> 1 | F6: =ROUNDUP(F5/4,0) -> 1 | G6: =ROUNDUP(G5/4,0) -> 1 | H6: =ROUNDUP(H5/4,0) -> 2 | I6: =ROUNDUP(I5/4,0) -> 2 | J6: =ROUNDUP(J5/4,0) -> 2 | K6: =ROUNDUP(K5/4,0) -> 2 | ... O6: =ROUNDUP(O5/4,0) -> 3 | Q6: 1 | R6: 2 | S6: 3
A7: Период | C7: Параметр | D7: ="Q"&(MOD(D5-1,4)+1)&" "&(2026+D6) -> Q1 2027 | E7: ="Q"&(MOD(E5-1,4)+1)&" "&(2026+E6) -> Q2 2027 | F7: ="Q"&(MOD(F5-1,4)+1)&" "&(2026+F6) -> Q3 2027 | G7: ="Q"&(MOD(G5-1,4)+1)&" "&(2026+G6) -> Q4 2027 | H7: ="Q"&(MOD(H5-1,4)+1)&" "&(2026+H6) -> Q1 2028 | I7: ="Q"&(MOD(I5-1,4)+1)&" "&(2026+I6) -> Q2 2028 | J7: ="Q"&(MOD(J5-1,4)+1)&" "&(2026+J6) -> Q3 2028 | K7: ="Q"&(MOD(K5-1,4)+1)&" "&(2026+K6) -> Q4 2028 | ... O7: ="Q"&(MOD(O5-1,4)+1)&" "&(2026+O6) -> Q4 2029 | Q7: 2027 | R7: 2028 | S7: 2029 | T7: Итого
A9: Параметры сценария (из листа «Допущения»)
A10: Лимит инвестиций (потолок, не цель) | B10: млн ₽ | C10: =INDEX(Допущения!$C$6:$E$6,$C$2) -> 10000
A11: Максимальный срок окупаемости | B11: кварталов | C11: =INDEX(Допущения!$C$7:$E$7,$C$2) -> 12
A12: Ставка дисконтирования (годовая) | B12: % год | C12: =INDEX(Допущения!$C$8:$E$8,$C$2) -> 0.15
A13: Маржа инкрементального дохода (после переменных издержек сделок) | B13: % | C13: =INDEX(Допущения!$C$9:$E$9,$C$2) -> 0.85
A14: Товарные сделки на платформе в год (база 2026) | B14: млн шт. | C14: =INDEX(Допущения!$C$11:$E$11,$C$2) -> 200
A15: Рост числа товарных сделок в год | B15: % год | C15: =INDEX(Допущения!$C$12:$E$12,$C$2) -> 0.1
A16: Доля товарных сделок с Авито Доставкой (2026) | B16: % | C16: =INDEX(Допущения!$C$13:$E$13,$C$2) -> 0.43
A17: Рост доли Доставки в год | B17: п.п./год | C17: =INDEX(Допущения!$C$14:$E$14,$C$2) -> 0.04
A18: Месячная аудитория Авито | B18: млн чел. | C18: =INDEX(Допущения!$C$15:$E$15,$C$2) -> 51
A19: Доля сделок Доставки в охваченных категориях — Год 1 | B19: % | C19: =INDEX(Допущения!$C$17:$E$17,$C$2) -> 0.39
A20: то же — Год 2 | B20: % | C20: =INDEX(Допущения!$C$18:$E$18,$C$2) -> 0.62
A21: то же — Год 3 | B21: % | C21: =INDEX(Допущения!$C$19:$E$19,$C$2) -> 0.78
A22: Доля сделок, идущих через карточки с блоком опыта (на зрелости) | B22: % | C22: =INDEX(Допущения!$C$20:$E$20,$C$2) -> 0.55
A23: Доля подтверждённых покупателей, оставивших отзыв о модели (на зрелости) | B23: % | C23: =INDEX(Допущения!$C$22:$E$22,$C$2) -> 0.1
A24: Доля авторов, обновивших отзыв позже / с долгим сроком использования | B24: % | C24: =INDEX(Допущения!$C$23:$E$23,$C$2) -> 0.35
A25: Срок использования до пуша «оцените и продайте» | B25: кварталов | C25: =INDEX(Допущения!$C$24:$E$24,$C$2) -> 2
A26: Доля обновивших отзыв, выставивших вещь через «Можно продать» | B26: % | C26: =INDEX(Допущения!$C$25:$E$25,$C$2) -> 0.12
A27: Доля выставивших вещь, купивших продвижение | B27: % | C27: =INDEX(Допущения!$C$26:$E$26,$C$2) -> 0.25
A28: Средний платёж за продвижение | B28: ₽ | C28: =INDEX(Допущения!$C$27:$E$27,$C$2) -> 250
A29: Доля выставленных вещей, проданных через Доставку | B29: % | C29: =INDEX(Допущения!$C$28:$E$28,$C$2) -> 0.4
A30: Прирост конверсии в сделку в карточках с блоком (относительный) | B30: % | C30: =INDEX(Допущения!$C$30:$E$30,$C$2) -> 0.08
A31: Негативный эффект: потеря сделок в охваченных карточках (слабые модели, меньше контактов) | B31: % | C31: =INDEX(Допущения!$C$32:$E$32,$C$2) -> 0.0015
A32: Доля прироста, действительно инкрементальная | B32: % | C32: =INDEX(Допущения!$C$31:$E$31,$C$2) -> 0.85
A33: Средний чек сделки с Доставкой | B33: ₽ | C33: =INDEX(Допущения!$C$33:$E$33,$C$2) -> 2000
A34: Доход Авито с оборота сделки через Доставку | B34: % | C34: =INDEX(Допущения!$C$34:$E$34,$C$2) -> 0.125
A35: Индексация среднего чека и комиссии в год (сложный процент) | B35: % год | C35: =INDEX(Допущения!$C$35:$E$35,$C$2) -> 0.07
A36: Доход Авито с одной сделки через Доставку | B36: ₽ | C36: =$C$33*$C$34 -> 250
A37: Доля аудитории охваченных категорий, пользующаяся блоком в месяц (на зрелости) | B37: % | C37: =INDEX(Допущения!$C$37:$E$37,$C$2) -> 0.2
A38: Дополнительных визитов на участника в месяц | B38: визитов | C38: =INDEX(Допущения!$C$38:$E$38,$C$2) -> 1.1
A39: Просмотров за дополнительный визит | B39: шт. | C39: =INDEX(Допущения!$C$39:$E$39,$C$2) -> 12
A40: Доход от рекламы и рекомендаций на один просмотр | B40: ₽ | C40: =INDEX(Допущения!$C$40:$E$40,$C$2) -> 0.11
A41: Доп. сделок в год на участника за счёт удержания (по всей платформе) | B41: сделок/год | C41: =INDEX(Допущения!$C$42:$E$42,$C$2) -> 0.04
A42: Средний доход Авито со сделки на платформе | B42: ₽ | C42: =INDEX(Допущения!$C$43:$E$43,$C$2) -> 250
A43: Численность команды, Год 1 | B43: FTE | C43: =Допущения!C54*INDEX(Допущения!$C$57:$E$57,$C$2) -> 15
A44: Численность команды, Год 2 | B44: FTE | C44: =Допущения!D54*INDEX(Допущения!$C$57:$E$57,$C$2) -> 19
A45: Численность команды, Год 3 | B45: FTE | C45: =Допущения!E54*INDEX(Допущения!$C$57:$E$57,$C$2) -> 20
A46: Стоимость 1 FTE в месяц (с налогами и накладными) | B46: тыс. ₽ | C46: =INDEX(Допущения!$C$58:$E$58,$C$2) -> 450
A47: Индексация ФОТ в год | B47: % год | C47: =INDEX(Допущения!$C$59:$E$59,$C$2) -> 0.08
A48: Сообщений в обсуждениях на один отзыв | B48: шт. | C48: =INDEX(Допущения!$C$61:$E$61,$C$2) -> 2
A49: Стоимость ИИ-модерации одного объекта | B49: ₽ | C49: =INDEX(Допущения!$C$62:$E$62,$C$2) -> 1
A50: Доля спорных объектов (ручная проверка) | B50: % | C50: =INDEX(Допущения!$C$63:$E$63,$C$2) -> 0.03
A51: Стоимость ручной проверки | B51: ₽ | C51: =INDEX(Допущения!$C$64:$E$64,$C$2) -> 20
A52: ИИ: генерация пересказов и ИИ-ответов, на 1 отзыв | B52: ₽ | C52: =INDEX(Допущения!$C$65:$E$65,$C$2) -> 2
A53: Инфраструктура и хранение (фикс.) в квартал | B53: млн ₽ | C53: =INDEX(Допущения!$C$66:$E$66,$C$2) -> 3
A54: Первый квартал инфраструктурных затрат | B54: № кв. | C54: =INDEX(Допущения!$C$67:$E$67,$C$2) -> 2
A55: Доля отзывов, получающих бонус/пожертвование | B55: % | C55: =INDEX(Допущения!$C$68:$E$68,$C$2) -> 0.5
A56: Сумма бонуса/пожертвования за отзыв | B56: ₽ | C56: =INDEX(Допущения!$C$69:$E$69,$C$2) -> 25
A57: Годовой потолок бюджета на мотивацию | B57: млн ₽/год | C57: =INDEX(Допущения!$C$70:$E$70,$C$2) -> 200
A58: Резерв на непредвиденные затраты | B58: % | C58: =INDEX(Допущения!$C$71:$E$71,$C$2) -> 0.1
A59: Разовый маркетинг запуска | B59: млн ₽ | C59: =INDEX(Допущения!$C$73:$E$73,$C$2) -> 80
A60: Первый квартал маркетинга запуска | B60: № кв. | C60: =INDEX(Допущения!$C$74:$E$74,$C$2) -> 3
A61: Последний квартал маркетинга запуска | B61: № кв. | C61: =INDEX(Допущения!$C$75:$E$75,$C$2) -> 4
A62: Текущий маркетинг и тесты после запуска, в квартал | B62: млн ₽ | C62: =INDEX(Допущения!$C$76:$E$76,$C$2) -> 8
A64: A. Объёмы и охват
A65: Товарные сделки на платформе | B65: тыс. шт. | D65: =$C$14*1000*(1+$C$15)^D$6/4 -> 55000 | E65: =$C$14*1000*(1+$C$15)^E$6/4 -> 55000 | F65: =$C$14*1000*(1+$C$15)^F$6/4 -> 55000 | G65: =$C$14*1000*(1+$C$15)^G$6/4 -> 55000 | H65: =$C$14*1000*(1+$C$15)^H$6/4 -> 60500 | I65: =$C$14*1000*(1+$C$15)^I$6/4 -> 60500 | J65: =$C$14*1000*(1+$C$15)^J$6/4 -> 60500 | K65: =$C$14*1000*(1+$C$15)^K$6/4 -> 60500 | ... O65: =$C$14*1000*(1+$C$15)^O$6/4 -> 66550 | Q65: =SUMIF($D$6:$O$6,Q$6,$D65:$O65) -> 220000 | R65: =SUMIF($D$6:$O$6,R$6,$D65:$O65) -> 242000 | S65: =SUMIF($D$6:$O$6,S$6,$D65:$O65) -> 266200 | T65: =SUM(Q65:S65) -> 728200
A66: Доля сделок через Доставку | B66: % | D66: =$C$16+$C$17*D$6 -> 0.47 | E66: =$C$16+$C$17*E$6 -> 0.47 | F66: =$C$16+$C$17*F$6 -> 0.47 | G66: =$C$16+$C$17*G$6 -> 0.47 | H66: =$C$16+$C$17*H$6 -> 0.51 | I66: =$C$16+$C$17*I$6 -> 0.51 | J66: =$C$16+$C$17*J$6 -> 0.51 | K66: =$C$16+$C$17*K$6 -> 0.51 | ... O66: =$C$16+$C$17*O$6 -> 0.55
A67: Сделки через Доставку | B67: тыс. шт. | D67: =D65*D66 -> 25850 | E67: =E65*E66 -> 25850 | F67: =F65*F66 -> 25850 | G67: =G65*G66 -> 25850 | H67: =H65*H66 -> 30855 | I67: =I65*I66 -> 30855 | J67: =J65*J66 -> 30855 | K67: =K65*K66 -> 30855 | ... O67: =O65*O66 -> 36602.5 | Q67: =SUMIF($D$6:$O$6,Q$6,$D67:$O67) -> 103400 | R67: =SUMIF($D$6:$O$6,R$6,$D67:$O67) -> 123420 | S67: =SUMIF($D$6:$O$6,S$6,$D67:$O67) -> 146410 | T67: =SUM(Q67:S67) -> 373230
A68: Охват категорий механикой (доля сделок Доставки) | B68: % | D68: =INDEX($C$19:$C$21,D$6) -> 0.39 | E68: =INDEX($C$19:$C$21,E$6) -> 0.39 | F68: =INDEX($C$19:$C$21,F$6) -> 0.39 | G68: =INDEX($C$19:$C$21,G$6) -> 0.39 | H68: =INDEX($C$19:$C$21,H$6) -> 0.62 | I68: =INDEX($C$19:$C$21,I$6) -> 0.62 | J68: =INDEX($C$19:$C$21,J$6) -> 0.62 | K68: =INDEX($C$19:$C$21,K$6) -> 0.62 | ... O68: =INDEX($C$19:$C$21,O$6) -> 0.78
A69: Профиль зрелости запуска | B69: % | D69: =INDEX(Допущения!D$79:D$81,$C$2) -> 0 | E69: =INDEX(Допущения!E$79:E$81,$C$2) -> 0 | F69: =INDEX(Допущения!F$79:F$81,$C$2) -> 0.15 | G69: =INDEX(Допущения!G$79:G$81,$C$2) -> 0.35 | H69: =INDEX(Допущения!H$79:H$81,$C$2) -> 0.55 | I69: =INDEX(Допущения!I$79:I$81,$C$2) -> 0.75 | J69: =INDEX(Допущения!J$79:J$81,$C$2) -> 0.9 | K69: =INDEX(Допущения!K$79:K$81,$C$2) -> 1 | ... O69: =INDEX(Допущения!O$79:O$81,$C$2) -> 1
A70: Сделки Доставки в охваченных категориях | B70: тыс. шт. | D70: =D67*D68 -> 10081.5 | E70: =E67*E68 -> 10081.5 | F70: =F67*F68 -> 10081.5 | G70: =G67*G68 -> 10081.5 | H70: =H67*H68 -> 19130.1 | I70: =I67*I68 -> 19130.1 | J70: =J67*J68 -> 19130.1 | K70: =K67*K68 -> 19130.1 | ... O70: =O67*O68 -> 28549.95 | Q70: =SUMIF($D$6:$O$6,Q$6,$D70:$O70) -> 40326 | R70: =SUMIF($D$6:$O$6,R$6,$D70:$O70) -> 76520.4 | S70: =SUMIF($D$6:$O$6,S$6,$D70:$O70) -> 114199.8 | T70: =SUM(Q70:S70) -> 231046.2
A71: из них — в карточках с блоком опыта | B71: тыс. шт. | D71: =D70*$C$22*D69 -> 0 | E71: =E70*$C$22*E69 -> 0 | F71: =F70*$C$22*F69 -> 831.72375 | G71: =G70*$C$22*G69 -> 1940.6888 | H71: =H70*$C$22*H69 -> 5786.8552 | I71: =I70*$C$22*I69 -> 7891.1663 | J71: =J70*$C$22*J69 -> 9469.3995 | K71: =K70*$C$22*K69 -> 10521.555 | ... O71: =O70*$C$22*O69 -> 15702.472 | Q71: =SUMIF($D$6:$O$6,Q$6,$D71:$O71) -> 2772.4125 | R71: =SUMIF($D$6:$O$6,R$6,$D71:$O71) -> 33668.976 | S71: =SUMIF($D$6:$O$6,S$6,$D71:$O71) -> 62809.89 | T71: =SUM(Q71:S71) -> 99251.279
A73: B. Воронка отзывов
A74: Отзывы о моделях (подтверждённые покупатели) | B74: тыс. шт. | D74: =D70*D69*$C$23 -> 0 | E74: =E70*E69*$C$23 -> 0 | F74: =F70*F69*$C$23 -> 151.2225 | G74: =G70*G69*$C$23 -> 352.8525 | H74: =H70*H69*$C$23 -> 1052.1555 | I74: =I70*I69*$C$23 -> 1434.7575 | J74: =J70*J69*$C$23 -> 1721.709 | K74: =K70*K69*$C$23 -> 1913.01 | ... O74: =O70*O69*$C$23 -> 2854.995 | Q74: =SUMIF($D$6:$O$6,Q$6,$D74:$O74) -> 504.075 | R74: =SUMIF($D$6:$O$6,R$6,$D74:$O74) -> 6121.632 | S74: =SUMIF($D$6:$O$6,S$6,$D74:$O74) -> 11419.98 | T74: =SUM(Q74:S74) -> 18045.687
A75: Авторы с долгим сроком использования / обновили отзыв | B75: тыс. шт. | D75: =IF(D$5>$C$25,INDEX($D$74:$O$74,D$5-$C$25),0)*$C$24 -> 0 | E75: =IF(E$5>$C$25,INDEX($D$74:$O$74,E$5-$C$25),0)*$C$24 -> 0 | F75: =IF(F$5>$C$25,INDEX($D$74:$O$74,F$5-$C$25),0)*$C$24 -> 0 | G75: =IF(G$5>$C$25,INDEX($D$74:$O$74,G$5-$C$25),0)*$C$24 -> 0 | H75: =IF(H$5>$C$25,INDEX($D$74:$O$74,H$5-$C$25),0)*$C$24 -> 52.927875 | I75: =IF(I$5>$C$25,INDEX($D$74:$O$74,I$5-$C$25),0)*$C$24 -> 123.49837 | J75: =IF(J$5>$C$25,INDEX($D$74:$O$74,J$5-$C$25),0)*$C$24 -> 368.25443 | K75: =IF(K$5>$C$25,INDEX($D$74:$O$74,K$5-$C$25),0)*$C$24 -> 502.16512 | ... O75: =IF(O$5>$C$25,INDEX($D$74:$O$74,O$5-$C$25),0)*$C$24 -> 999.24825 | Q75: =SUMIF($D$6:$O$6,Q$6,$D75:$O75) -> 0 | R75: =SUMIF($D$6:$O$6,R$6,$D75:$O75) -> 1046.8458 | S75: =SUMIF($D$6:$O$6,S$6,$D75:$O75) -> 3270.6481 | T75: =SUM(Q75:S75) -> 4317.494
A76: Выставили вещь через «Можно продать» | B76: тыс. шт. | D76: =D75*$C$26 -> 0 | E76: =E75*$C$26 -> 0 | F76: =F75*$C$26 -> 0 | G76: =G75*$C$26 -> 0 | H76: =H75*$C$26 -> 6.351345 | I76: =I75*$C$26 -> 14.819805 | J76: =J75*$C$26 -> 44.190531 | K76: =K75*$C$26 -> 60.259815 | ... O76: =O75*$C$26 -> 119.90979 | Q76: =SUMIF($D$6:$O$6,Q$6,$D76:$O76) -> 0 | R76: =SUMIF($D$6:$O$6,R$6,$D76:$O76) -> 125.6215 | S76: =SUMIF($D$6:$O$6,S$6,$D76:$O76) -> 392.47778 | T76: =SUM(Q76:S76) -> 518.09927
A77: Купили продвижение | B77: тыс. шт. | D77: =D76*$C$27 -> 0 | E77: =E76*$C$27 -> 0 | F77: =F76*$C$27 -> 0 | G77: =G76*$C$27 -> 0 | H77: =H76*$C$27 -> 1.5878363 | I77: =I76*$C$27 -> 3.7049513 | J77: =J76*$C$27 -> 11.047633 | K77: =K76*$C$27 -> 15.064954 | ... O77: =O76*$C$27 -> 29.977448 | Q77: =SUMIF($D$6:$O$6,Q$6,$D77:$O77) -> 0 | R77: =SUMIF($D$6:$O$6,R$6,$D77:$O77) -> 31.405374 | S77: =SUMIF($D$6:$O$6,S$6,$D77:$O77) -> 98.119445 | T77: =SUM(Q77:S77) -> 129.52482
A79: C. Эффекты (дополнительная выручка Авито)
A80: Доход Авито с одной сделки через Доставку (с индексацией) | B80: ₽ | D80: =$C$36*(1+$C$35)^(D$6-1) -> 250 | E80: =$C$36*(1+$C$35)^(E$6-1) -> 250 | F80: =$C$36*(1+$C$35)^(F$6-1) -> 250 | G80: =$C$36*(1+$C$35)^(G$6-1) -> 250 | H80: =$C$36*(1+$C$35)^(H$6-1) -> 267.5 | I80: =$C$36*(1+$C$35)^(I$6-1) -> 267.5 | J80: =$C$36*(1+$C$35)^(J$6-1) -> 267.5 | K80: =$C$36*(1+$C$35)^(K$6-1) -> 267.5 | ... O80: =$C$36*(1+$C$35)^(O$6-1) -> 286.225 | Q80: =AVERAGEIF($D$6:$O$6,Q$6,$D80:$O80) -> 250 | R80: =AVERAGEIF($D$6:$O$6,R$6,$D80:$O80) -> 267.5 | S80: =AVERAGEIF($D$6:$O$6,S$6,$D80:$O80) -> 286.225
A81: Эффект 1: прирост сделок (инкрементальный) | B81: тыс. шт. | D81: =D71*$C$30*$C$32 -> 0 | E81: =E71*$C$30*$C$32 -> 0 | F81: =F71*$C$30*$C$32 -> 56.557215 | G81: =G71*$C$30*$C$32 -> 131.96684 | H81: =H71*$C$30*$C$32 -> 393.50616 | I81: =I71*$C$30*$C$32 -> 536.5993 | J81: =J71*$C$30*$C$32 -> 643.91917 | K81: =K71*$C$30*$C$32 -> 715.46574 | ... O81: =O71*$C$30*$C$32 -> 1067.7681 | Q81: =SUMIF($D$6:$O$6,Q$6,$D81:$O81) -> 188.52405 | R81: =SUMIF($D$6:$O$6,R$6,$D81:$O81) -> 2289.4904 | S81: =SUMIF($D$6:$O$6,S$6,$D81:$O81) -> 4271.0725 | T81: =SUM(Q81:S81) -> 6749.0869
A82: Эффект 1: потеря сделок (слабые модели, меньше контактов) | B82: тыс. шт. | D82: =D71*$C$31 -> 0 | E82: =E71*$C$31 -> 0 | F82: =F71*$C$31 -> 1.2475856 | G82: =G71*$C$31 -> 2.9110331 | H82: =H71*$C$31 -> 8.6802829 | I82: =I71*$C$31 -> 11.836749 | J82: =J71*$C$31 -> 14.204099 | K82: =K71*$C$31 -> 15.782333 | ... O82: =O71*$C$31 -> 23.553709 | Q82: =SUMIF($D$6:$O$6,Q$6,$D82:$O82) -> 4.1586187 | R82: =SUMIF($D$6:$O$6,R$6,$D82:$O82) -> 50.503464 | S82: =SUMIF($D$6:$O$6,S$6,$D82:$O82) -> 94.214835 | T82: =SUM(Q82:S82) -> 148.87692
A83: Эффект 1: чистый прирост сделок | B83: тыс. шт. | D83: =D81-D82 -> 0 | E83: =E81-E82 -> 0 | F83: =F81-F82 -> 55.309629 | G83: =G81-G82 -> 129.0558 | H83: =H81-H82 -> 384.82587 | I83: =I81-I82 -> 524.76256 | J83: =J81-J82 -> 629.71507 | K83: =K81-K82 -> 699.68341 | ... O83: =O81-O82 -> 1044.2144 | Q83: =SUMIF($D$6:$O$6,Q$6,$D83:$O83) -> 184.36543 | R83: =SUMIF($D$6:$O$6,R$6,$D83:$O83) -> 2238.9869 | S83: =SUMIF($D$6:$O$6,S$6,$D83:$O83) -> 4176.8577 | T83: =SUM(Q83:S83) -> 6600.21
A84: Эффект 1: доход от конверсии (комиссия Доставки) | B84: млн ₽ | D84: =D83*D80/1000 -> 0 | E84: =E83*E80/1000 -> 0 | F84: =F83*F80/1000 -> 13.827407 | G84: =G83*G80/1000 -> 32.26395 | H84: =H83*H80/1000 -> 102.94092 | I84: =I83*I80/1000 -> 140.37398 | J84: =J83*J80/1000 -> 168.44878 | K84: =K83*K80/1000 -> 187.16531 | ... O84: =O83*O80/1000 -> 298.88027 | Q84: =SUMIF($D$6:$O$6,Q$6,$D84:$O84) -> 46.091358 | R84: =SUMIF($D$6:$O$6,R$6,$D84:$O84) -> 598.929 | S84: =SUMIF($D$6:$O$6,S$6,$D84:$O84) -> 1195.5211 | T84: =SUM(Q84:S84) -> 1840.5414
A85: Эффект 2: доход от продвижения новых объявлений | B85: млн ₽ | D85: =D77*$C$28/1000 -> 0 | E85: =E77*$C$28/1000 -> 0 | F85: =F77*$C$28/1000 -> 0 | G85: =G77*$C$28/1000 -> 0 | H85: =H77*$C$28/1000 -> 0.39695906 | I85: =I77*$C$28/1000 -> 0.92623781 | J85: =J77*$C$28/1000 -> 2.7619082 | K85: =K77*$C$28/1000 -> 3.7662384 | ... O85: =O77*$C$28/1000 -> 7.4943619 | Q85: =SUMIF($D$6:$O$6,Q$6,$D85:$O85) -> 0 | R85: =SUMIF($D$6:$O$6,R$6,$D85:$O85) -> 7.8513435 | S85: =SUMIF($D$6:$O$6,S$6,$D85:$O85) -> 24.529861 | T85: =SUM(Q85:S85) -> 32.381205
A86: Эффект 2: доход со сделок по новым объявлениям | B86: млн ₽ | D86: =D76*$C$29*D80/1000 -> 0 | E86: =E76*$C$29*E80/1000 -> 0 | F86: =F76*$C$29*F80/1000 -> 0 | G86: =G76*$C$29*G80/1000 -> 0 | H86: =H76*$C$29*H80/1000 -> 0.67959391 | I86: =I76*$C$29*I80/1000 -> 1.5857191 | J86: =J76*$C$29*J80/1000 -> 4.7283868 | K86: =K76*$C$29*K80/1000 -> 6.4478002 | ... O86: =O76*$C$29*O80/1000 -> 13.728472 | Q86: =SUMIF($D$6:$O$6,Q$6,$D86:$O86) -> 0 | R86: =SUMIF($D$6:$O$6,R$6,$D86:$O86) -> 13.4415 | S86: =SUMIF($D$6:$O$6,S$6,$D86:$O86) -> 44.934781 | T86: =SUM(Q86:S86) -> 58.376281
A87: Участники блока в месяц (аудитория) | B87: тыс. чел. | D87: =$C$18*1000*D68*$C$37*D69 -> 0 | E87: =$C$18*1000*E68*$C$37*E69 -> 0 | F87: =$C$18*1000*F68*$C$37*F69 -> 596.7 | G87: =$C$18*1000*G68*$C$37*G69 -> 1392.3 | H87: =$C$18*1000*H68*$C$37*H69 -> 3478.2 | I87: =$C$18*1000*I68*$C$37*I69 -> 4743 | J87: =$C$18*1000*J68*$C$37*J69 -> 5691.6 | K87: =$C$18*1000*K68*$C$37*K69 -> 6324 | ... O87: =$C$18*1000*O68*$C$37*O69 -> 7956 | Q87: =AVERAGEIF($D$6:$O$6,Q$6,$D87:$O87) -> 497.25 | R87: =AVERAGEIF($D$6:$O$6,R$6,$D87:$O87) -> 5059.2 | S87: =AVERAGEIF($D$6:$O$6,S$6,$D87:$O87) -> 7956
A88: Эффект 3: дополнительные просмотры за квартал | B88: тыс. шт. | D88: =D87*$C$38*3*$C$39 -> 0 | E88: =E87*$C$38*3*$C$39 -> 0 | F88: =F87*$C$38*3*$C$39 -> 23629.32 | G88: =G87*$C$38*3*$C$39 -> 55135.08 | H88: =H87*$C$38*3*$C$39 -> 137736.72 | I88: =I87*$C$38*3*$C$39 -> 187822.8 | J88: =J87*$C$38*3*$C$39 -> 225387.36 | K88: =K87*$C$38*3*$C$39 -> 250430.4 | ... O88: =O87*$C$38*3*$C$39 -> 315057.6 | Q88: =SUMIF($D$6:$O$6,Q$6,$D88:$O88) -> 78764.4 | R88: =SUMIF($D$6:$O$6,R$6,$D88:$O88) -> 801377.28 | S88: =SUMIF($D$6:$O$6,S$6,$D88:$O88) -> 1260230.4 | T88: =SUM(Q88:S88) -> 2140372.1
A89: Эффект 3: доход от рекламы и рекомендаций | B89: млн ₽ | D89: =D88*$C$40/1000 -> 0 | E89: =E88*$C$40/1000 -> 0 | F89: =F88*$C$40/1000 -> 2.5992252 | G89: =G88*$C$40/1000 -> 6.0648588 | H89: =H88*$C$40/1000 -> 15.151039 | I89: =I88*$C$40/1000 -> 20.660508 | J89: =J88*$C$40/1000 -> 24.79261 | K89: =K88*$C$40/1000 -> 27.547344 | ... O89: =O88*$C$40/1000 -> 34.656336 | Q89: =SUMIF($D$6:$O$6,Q$6,$D89:$O89) -> 8.664084 | R89: =SUMIF($D$6:$O$6,R$6,$D89:$O89) -> 88.151501 | S89: =SUMIF($D$6:$O$6,S$6,$D89:$O89) -> 138.62534 | T89: =SUM(Q89:S89) -> 235.44093
A90: Эффект 4: удержание (верхний сценарий) | B90: млн ₽ | D90: =D87*$C$41/4*$C$42/1000 -> 0 | E90: =E87*$C$41/4*$C$42/1000 -> 0 | F90: =F87*$C$41/4*$C$42/1000 -> 1.49175 | G90: =G87*$C$41/4*$C$42/1000 -> 3.48075 | H90: =H87*$C$41/4*$C$42/1000 -> 8.6955 | I90: =I87*$C$41/4*$C$42/1000 -> 11.8575 | J90: =J87*$C$41/4*$C$42/1000 -> 14.229 | K90: =K87*$C$41/4*$C$42/1000 -> 15.81 | ... O90: =O87*$C$41/4*$C$42/1000 -> 19.89 | Q90: =SUMIF($D$6:$O$6,Q$6,$D90:$O90) -> 4.9725 | R90: =SUMIF($D$6:$O$6,R$6,$D90:$O90) -> 50.592 | S90: =SUMIF($D$6:$O$6,S$6,$D90:$O90) -> 79.56 | T90: =SUM(Q90:S90) -> 135.1245
A91: Дополнительная выручка всего | B91: млн ₽ | D91: =D84+D85+D86+D89+D90 -> 0 | E91: =E84+E85+E86+E89+E90 -> 0 | F91: =F84+F85+F86+F89+F90 -> 17.918383 | G91: =G84+G85+G86+G89+G90 -> 41.809559 | H91: =H84+H85+H86+H89+H90 -> 127.86401 | I91: =I84+I85+I86+I89+I90 -> 175.40395 | J91: =J84+J85+J86+J89+J90 -> 214.96068 | K91: =K84+K85+K86+K89+K90 -> 240.73669 | ... O91: =O84+O85+O86+O89+O90 -> 374.64944 | Q91: =SUMIF($D$6:$O$6,Q$6,$D91:$O91) -> 59.727942 | R91: =SUMIF($D$6:$O$6,R$6,$D91:$O91) -> 758.96534 | S91: =SUMIF($D$6:$O$6,S$6,$D91:$O91) -> 1483.1711 | T91: =SUM(Q91:S91) -> 2301.8644
A92: Маржинальный доход (после переменных издержек) | B92: млн ₽ | D92: =D91*$C$13 -> 0 | E92: =E91*$C$13 -> 0 | F92: =F91*$C$13 -> 15.230625 | G92: =G91*$C$13 -> 35.538125 | H92: =H91*$C$13 -> 108.68441 | I92: =I91*$C$13 -> 149.09336 | J92: =J91*$C$13 -> 182.71658 | K92: =K91*$C$13 -> 204.62619 | ... O92: =O91*$C$13 -> 318.45203 | Q92: =SUMIF($D$6:$O$6,Q$6,$D92:$O92) -> 50.768751 | R92: =SUMIF($D$6:$O$6,R$6,$D92:$O92) -> 645.12054 | S92: =SUMIF($D$6:$O$6,S$6,$D92:$O92) -> 1260.6954 | T92: =SUM(Q92:S92) -> 1956.5847
A94: D. Затраты
A95: Численность команды | B95: FTE | D95: =INDEX($C$43:$C$45,D$6) -> 15 | E95: =INDEX($C$43:$C$45,E$6) -> 15 | F95: =INDEX($C$43:$C$45,F$6) -> 15 | G95: =INDEX($C$43:$C$45,G$6) -> 15 | H95: =INDEX($C$43:$C$45,H$6) -> 19 | I95: =INDEX($C$43:$C$45,I$6) -> 19 | J95: =INDEX($C$43:$C$45,J$6) -> 19 | K95: =INDEX($C$43:$C$45,K$6) -> 19 | ... O95: =INDEX($C$43:$C$45,O$6) -> 20 | Q95: =AVERAGEIF($D$6:$O$6,Q$6,$D95:$O95) -> 15 | R95: =AVERAGEIF($D$6:$O$6,R$6,$D95:$O95) -> 19 | S95: =AVERAGEIF($D$6:$O$6,S$6,$D95:$O95) -> 20
A96: Команда разработки | B96: млн ₽ | D96: =D95*$C$46*3*(1+$C$47)^(D$6-1)/1000 -> 20.25 | E96: =E95*$C$46*3*(1+$C$47)^(E$6-1)/1000 -> 20.25 | F96: =F95*$C$46*3*(1+$C$47)^(F$6-1)/1000 -> 20.25 | G96: =G95*$C$46*3*(1+$C$47)^(G$6-1)/1000 -> 20.25 | H96: =H95*$C$46*3*(1+$C$47)^(H$6-1)/1000 -> 27.702 | I96: =I95*$C$46*3*(1+$C$47)^(I$6-1)/1000 -> 27.702 | J96: =J95*$C$46*3*(1+$C$47)^(J$6-1)/1000 -> 27.702 | K96: =K95*$C$46*3*(1+$C$47)^(K$6-1)/1000 -> 27.702 | ... O96: =O95*$C$46*3*(1+$C$47)^(O$6-1)/1000 -> 31.4928 | Q96: =SUMIF($D$6:$O$6,Q$6,$D96:$O96) -> 81 | R96: =SUMIF($D$6:$O$6,R$6,$D96:$O96) -> 110.808 | S96: =SUMIF($D$6:$O$6,S$6,$D96:$O96) -> 125.9712 | T96: =SUM(Q96:S96) -> 317.7792
A97: Объекты модерации (отзывы + сообщения) | B97: тыс. шт. | D97: =D74*(1+$C$48) -> 0 | E97: =E74*(1+$C$48) -> 0 | F97: =F74*(1+$C$48) -> 453.6675 | G97: =G74*(1+$C$48) -> 1058.5575 | H97: =H74*(1+$C$48) -> 3156.4665 | I97: =I74*(1+$C$48) -> 4304.2725 | J97: =J74*(1+$C$48) -> 5165.127 | K97: =K74*(1+$C$48) -> 5739.03 | ... O97: =O74*(1+$C$48) -> 8564.985 | Q97: =SUMIF($D$6:$O$6,Q$6,$D97:$O97) -> 1512.225 | R97: =SUMIF($D$6:$O$6,R$6,$D97:$O97) -> 18364.896 | S97: =SUMIF($D$6:$O$6,S$6,$D97:$O97) -> 34259.94 | T97: =SUM(Q97:S97) -> 54137.061
A98: ИИ-модерация | B98: млн ₽ | D98: =D97*$C$49/1000 -> 0 | E98: =E97*$C$49/1000 -> 0 | F98: =F97*$C$49/1000 -> 0.4536675 | G98: =G97*$C$49/1000 -> 1.0585575 | H98: =H97*$C$49/1000 -> 3.1564665 | I98: =I97*$C$49/1000 -> 4.3042725 | J98: =J97*$C$49/1000 -> 5.165127 | K98: =K97*$C$49/1000 -> 5.73903 | ... O98: =O97*$C$49/1000 -> 8.564985 | Q98: =SUMIF($D$6:$O$6,Q$6,$D98:$O98) -> 1.512225 | R98: =SUMIF($D$6:$O$6,R$6,$D98:$O98) -> 18.364896 | S98: =SUMIF($D$6:$O$6,S$6,$D98:$O98) -> 34.25994 | T98: =SUM(Q98:S98) -> 54.137061
A99: Ручная модерация спорных случаев | B99: млн ₽ | D99: =D97*$C$50*$C$51/1000 -> 0 | E99: =E97*$C$50*$C$51/1000 -> 0 | F99: =F97*$C$50*$C$51/1000 -> 0.2722005 | G99: =G97*$C$50*$C$51/1000 -> 0.6351345 | H99: =H97*$C$50*$C$51/1000 -> 1.8938799 | I99: =I97*$C$50*$C$51/1000 -> 2.5825635 | J99: =J97*$C$50*$C$51/1000 -> 3.0990762 | K99: =K97*$C$50*$C$51/1000 -> 3.443418 | ... O99: =O97*$C$50*$C$51/1000 -> 5.138991 | Q99: =SUMIF($D$6:$O$6,Q$6,$D99:$O99) -> 0.907335 | R99: =SUMIF($D$6:$O$6,R$6,$D99:$O99) -> 11.018938 | S99: =SUMIF($D$6:$O$6,S$6,$D99:$O99) -> 20.555964 | T99: =SUM(Q99:S99) -> 32.482237
A100: ИИ и инфраструктура | B100: млн ₽ | D100: =D74*$C$52/1000+IF(D$5>=$C$54,$C$53,0) -> 0 | E100: =E74*$C$52/1000+IF(E$5>=$C$54,$C$53,0) -> 3 | F100: =F74*$C$52/1000+IF(F$5>=$C$54,$C$53,0) -> 3.302445 | G100: =G74*$C$52/1000+IF(G$5>=$C$54,$C$53,0) -> 3.705705 | H100: =H74*$C$52/1000+IF(H$5>=$C$54,$C$53,0) -> 5.104311 | I100: =I74*$C$52/1000+IF(I$5>=$C$54,$C$53,0) -> 5.869515 | J100: =J74*$C$52/1000+IF(J$5>=$C$54,$C$53,0) -> 6.443418 | K100: =K74*$C$52/1000+IF(K$5>=$C$54,$C$53,0) -> 6.82602 | ... O100: =O74*$C$52/1000+IF(O$5>=$C$54,$C$53,0) -> 8.70999 | Q100: =SUMIF($D$6:$O$6,Q$6,$D100:$O100) -> 10.00815 | R100: =SUMIF($D$6:$O$6,R$6,$D100:$O100) -> 24.243264 | S100: =SUMIF($D$6:$O$6,S$6,$D100:$O100) -> 34.83996 | T100: =SUM(Q100:S100) -> 69.091374
A101: Мотивация авторов (с годовым потолком) | B101: млн ₽ | D101: =MIN(D74*$C$55*$C$56/1000,$C$57/4) -> 0 | E101: =MIN(E74*$C$55*$C$56/1000,$C$57/4) -> 0 | F101: =MIN(F74*$C$55*$C$56/1000,$C$57/4) -> 1.8902812 | G101: =MIN(G74*$C$55*$C$56/1000,$C$57/4) -> 4.4106562 | H101: =MIN(H74*$C$55*$C$56/1000,$C$57/4) -> 13.151944 | I101: =MIN(I74*$C$55*$C$56/1000,$C$57/4) -> 17.934469 | J101: =MIN(J74*$C$55*$C$56/1000,$C$57/4) -> 21.521362 | K101: =MIN(K74*$C$55*$C$56/1000,$C$57/4) -> 23.912625 | ... O101: =MIN(O74*$C$55*$C$56/1000,$C$57/4) -> 35.687438 | Q101: =SUMIF($D$6:$O$6,Q$6,$D101:$O101) -> 6.3009375 | R101: =SUMIF($D$6:$O$6,R$6,$D101:$O101) -> 76.5204 | S101: =SUMIF($D$6:$O$6,S$6,$D101:$O101) -> 142.74975 | T101: =SUM(Q101:S101) -> 225.57109
A102: Маркетинг (запуск + текущий) | B102: млн ₽ | D102: =IF(AND(D$5>=$C$60,D$5<=$C$61),$C$59/($C$61-$C$60+1),0)+IF(D$5>$C$61,$C$62,0) -> 0 | E102: =IF(AND(E$5>=$C$60,E$5<=$C$61),$C$59/($C$61-$C$60+1),0)+IF(E$5>$C$61,$C$62,0) -> 0 | F102: =IF(AND(F$5>=$C$60,F$5<=$C$61),$C$59/($C$61-$C$60+1),0)+IF(F$5>$C$61,$C$62,0) -> 40 | G102: =IF(AND(G$5>=$C$60,G$5<=$C$61),$C$59/($C$61-$C$60+1),0)+IF(G$5>$C$61,$C$62,0) -> 40 | H102: =IF(AND(H$5>=$C$60,H$5<=$C$61),$C$59/($C$61-$C$60+1),0)+IF(H$5>$C$61,$C$62,0) -> 8 | I102: =IF(AND(I$5>=$C$60,I$5<=$C$61),$C$59/($C$61-$C$60+1),0)+IF(I$5>$C$61,$C$62,0) -> 8 | J102: =IF(AND(J$5>=$C$60,J$5<=$C$61),$C$59/($C$61-$C$60+1),0)+IF(J$5>$C$61,$C$62,0) -> 8 | K102: =IF(AND(K$5>=$C$60,K$5<=$C$61),$C$59/($C$61-$C$60+1),0)+IF(K$5>$C$61,$C$62,0) -> 8 | ... O102: =IF(AND(O$5>=$C$60,O$5<=$C$61),$C$59/($C$61-$C$60+1),0)+IF(O$5>$C$61,$C$62,0) -> 8 | Q102: =SUMIF($D$6:$O$6,Q$6,$D102:$O102) -> 80 | R102: =SUMIF($D$6:$O$6,R$6,$D102:$O102) -> 32 | S102: =SUMIF($D$6:$O$6,S$6,$D102:$O102) -> 32 | T102: =SUM(Q102:S102) -> 144
A103: Затраты до резерва | B103: млн ₽ | D103: =D96+D98+D99+D100+D101+D102 -> 20.25 | E103: =E96+E98+E99+E100+E101+E102 -> 23.25 | F103: =F96+F98+F99+F100+F101+F102 -> 66.168594 | G103: =G96+G98+G99+G100+G101+G102 -> 70.060053 | H103: =H96+H98+H99+H100+H101+H102 -> 59.008601 | I103: =I96+I98+I99+I100+I101+I102 -> 66.39282 | J103: =J96+J98+J99+J100+J101+J102 -> 71.930984 | K103: =K96+K98+K99+K100+K101+K102 -> 75.623093 | ... O103: =O96+O98+O99+O100+O101+O102 -> 97.594204 | Q103: =SUMIF($D$6:$O$6,Q$6,$D103:$O103) -> 179.72865 | R103: =SUMIF($D$6:$O$6,R$6,$D103:$O103) -> 272.9555 | S103: =SUMIF($D$6:$O$6,S$6,$D103:$O103) -> 390.37681 | T103: =SUM(Q103:S103) -> 843.06096
A104: Резерв | B104: млн ₽ | D104: =D103*$C$58 -> 2.025 | E104: =E103*$C$58 -> 2.325 | F104: =F103*$C$58 -> 6.6168594 | G104: =G103*$C$58 -> 7.0060053 | H104: =H103*$C$58 -> 5.9008601 | I104: =I103*$C$58 -> 6.639282 | J104: =J103*$C$58 -> 7.1930984 | K104: =K103*$C$58 -> 7.5623093 | ... O104: =O103*$C$58 -> 9.7594203 | Q104: =SUMIF($D$6:$O$6,Q$6,$D104:$O104) -> 17.972865 | R104: =SUMIF($D$6:$O$6,R$6,$D104:$O104) -> 27.29555 | S104: =SUMIF($D$6:$O$6,S$6,$D104:$O104) -> 39.037681 | T104: =SUM(Q104:S104) -> 84.306096
A105: Затраты всего | B105: млн ₽ | D105: =D103+D104 -> 22.275 | E105: =E103+E104 -> 25.575 | F105: =F103+F104 -> 72.785454 | G105: =G103+G104 -> 77.066059 | H105: =H103+H104 -> 64.909461 | I105: =I103+I104 -> 73.032102 | J105: =J103+J104 -> 79.124082 | K105: =K103+K104 -> 83.185402 | ... O105: =O103+O104 -> 107.35362 | Q105: =SUMIF($D$6:$O$6,Q$6,$D105:$O105) -> 197.70151 | R105: =SUMIF($D$6:$O$6,R$6,$D105:$O105) -> 300.25105 | S105: =SUMIF($D$6:$O$6,S$6,$D105:$O105) -> 429.4145 | T105: =SUM(Q105:S105) -> 927.36706
...

Sheet Источники
A1: Данные кейса и открытые источники, использованные в модели
A3: Показатель | B3: Значение | C3: Источник / как использовано
A4: Лимит инвестиций | B4: до 10 млрд ₽ за 3 года | C4: Кейс. Потолок, не цель.
A5: Срок окупаемости | B5: до 3 лет | C5: Кейс.
A6: Сделки в Авито Товарах за год | B6: более 200 млн (2023) | C6: Forbes, А. Гевлич.
A7: Доля товарных сделок с Доставкой | B7: 27% (I пол. 2024) → 37% (I пол. 2025) | C7: МойСклад/Авито.
A8: Рост заказов с доставкой | B8: +30% в 2025 к 2024 | C8: Retail.ru/Авито.
A9: Категории в заказах с Доставкой | B9: одежда 30%, хобби 15%, запчасти 10%, красота 8%, спорт 6% (2025) | C9: Retail.ru. База охвата стартовых категорий.
A10: Месячная аудитория | B10: более 51 млн (сентябрь 2026) | C10: Кейс.
A11: Отзывы после покупки | B11: товары >23%, услуги >17% сделок | C11: Авито, ComNews (2024). Ориентир для доли отзывов.
A12: Видео в объявлениях | B12: +6–10% взаимодействий | C12: Авито. Ориентир для прироста конверсии.
A13: Средний чек сделки с Доставкой | B13: около 2 000 ₽ | C13: Созвон команды.
A14: Комиссия Авито со сделки | B14: около 250 ₽ | C14: Созвон команды.
... A18: Вопросы и ответы | B18: 74% читают; 24% подозрительнее без Q&A | C18: PowerReviews/1WorldSync, опрос ~16 тыс.
A20: Логика модели
A21: Воронка: сделки в стартовых категориях → отзыв → обновление отзыва → выставление вещи.
A22: Эффект 1: сделки в карточках с блоком × прирост конверсии × доля инкрементальных − потери, × доход со сделки.
A23: Эффект 2: авторы с долгим сроком × доля выставивших × (продвижение + доход со сделки).
A24: Эффект 3: доп. визиты × просмотры × доход на просмотр. Эффект 4 — только в оптимисте.
A25: Затраты: команда, модерация, ИИ и инфраструктура, мотивация авторов, маркетинг, резерв.
A26: Упрощения: без сезонности и налогов; общий профиль зрелости для всех категорий.
A28: Открытые вопросы к команде
A29: ☐ Какие 3–5 категорий берём на старт.
A30: ☐ Мотивация авторов: бонусы или пожертвование.
A31: ☐ Остаёмся в товарах или расширяем на другие направления.
A32: ☐ Где живут обсуждения: категории, модели или оба уровня.
A33: ☐ Рабочее название для презентации.
